{"int":{"st":"ESERCIZIO","c_ele":9,"t_ele":"Referendum","f_elet":"VOTANTI","dt_ele":20250608000000,"l_terr":"REGIONE","area":"I","dt_agg":20250609213247},"note":null,"scheda":[{"cod":5,"desc":null}],"enti":{"ente_p":{"desc":"SICILIA","cod":19,"ele_m":1850307,"ele_f":2015159,"ele_t":3865466,"com":[{"cod_reg":19,"com_att":4,"num_com":4}],"com_vot":[{"com":1,"dt_com":20250608120000,"scheda":5,"enti_p":5306,"enti_t":5306,"perc":"4,47","vot_m":0,"vot_f":0,"vot_t":172646,"perc_r":null},{"com":2,"dt_com":20250608190000,"scheda":5,"enti_p":5306,"enti_t":5306,"perc":"10,59","vot_m":0,"vot_f":0,"vot_t":409344,"perc_r":null},{"com":3,"dt_com":20250608230000,"scheda":5,"enti_p":5306,"enti_t":5306,"perc":"16,31","vot_m":0,"vot_f":0,"vot_t":630593,"perc_r":null},{"com":4,"dt_com":20250609150000,"scheda":5,"enti_p":5306,"enti_t":5306,"perc":"23,09","vot_m":416817,"vot_f":475891,"vot_t":892708,"perc_r":null}]},"enti_f":[{"tipo":"PROVINCIA","desc":"AGRIGENTO","cod":1,"ele_m":159666,"ele_f":173689,"ele_t":333355,"com_vot":[{"com":1,"dt_com":20250608120000,"scheda":5,"enti_p":512,"enti_t":512,"perc":"3,23","vot_m":0,"vot_f":0,"vot_t":10768,"perc_r":null},{"com":2,"dt_com":20250608190000,"scheda":5,"enti_p":512,"enti_t":512,"perc":"8,31","vot_m":0,"vot_f":0,"vot_t":27702,"perc_r":null},{"com":3,"dt_com":20250608230000,"scheda":5,"enti_p":512,"enti_t":512,"perc":"13,36","vot_m":0,"vot_f":0,"vot_t":44530,"perc_r":null},{"com":4,"dt_com":20250609150000,"scheda":5,"enti_p":512,"enti_t":512,"perc":"19,60","vot_m":30956,"vot_f":34374,"vot_t":65330,"perc_r":null}]},{"tipo":"PROVINCIA","desc":"CALTANISSETTA","cod":18,"ele_m":95861,"ele_f":105624,"ele_t":201485,"com_vot":[{"com":1,"dt_com":20250608120000,"scheda":5,"enti_p":289,"enti_t":289,"perc":"3,27","vot_m":0,"vot_f":0,"vot_t":6583,"perc_r":null},{"com":2,"dt_com":20250608190000,"scheda":5,"enti_p":289,"enti_t":289,"perc":"8,45","vot_m":0,"vot_f":0,"vot_t":17026,"perc_r":null},{"com":3,"dt_com":20250608230000,"scheda":5,"enti_p":289,"enti_t":289,"perc":"13,90","vot_m":0,"vot_f":0,"vot_t":28003,"perc_r":null},{"com":4,"dt_com":20250609150000,"scheda":5,"enti_p":289,"enti_t":289,"perc":"19,85","vot_m":18834,"vot_f":21152,"vot_t":39986,"perc_r":null}]},{"tipo":"PROVINCIA","desc":"CATANIA","cod":21,"ele_m":411793,"ele_f":450553,"ele_t":862346,"com_vot":[{"com":1,"dt_com":20250608120000,"scheda":5,"enti_p":1126,"enti_t":1126,"perc":"4,79","vot_m":0,"vot_f":0,"vot_t":41270,"perc_r":null},{"com":2,"dt_com":20250608190000,"scheda":5,"enti_p":1126,"enti_t":1126,"perc":"10,85","vot_m":0,"vot_f":0,"vot_t":93523,"perc_r":null},{"com":3,"dt_com":20250608230000,"scheda":5,"enti_p":1126,"enti_t":1126,"perc":"17,00","vot_m":0,"vot_f":0,"vot_t":146583,"perc_r":null},{"com":4,"dt_com":20250609150000,"scheda":5,"enti_p":1126,"enti_t":1126,"perc":"24,02","vot_m":96235,"vot_f":110940,"vot_t":207175,"perc_r":null}]},{"tipo":"PROVINCIA","desc":"ENNA","cod":28,"ele_m":60535,"ele_f":66203,"ele_t":126738,"com_vot":[{"com":1,"dt_com":20250608120000,"scheda":5,"enti_p":225,"enti_t":225,"perc":"3,89","vot_m":0,"vot_f":0,"vot_t":4928,"perc_r":null},{"com":2,"dt_com":20250608190000,"scheda":5,"enti_p":225,"enti_t":225,"perc":"10,26","vot_m":0,"vot_f":0,"vot_t":13005,"perc_r":null},{"com":3,"dt_com":20250608230000,"scheda":5,"enti_p":225,"enti_t":225,"perc":"17,99","vot_m":0,"vot_f":0,"vot_t":22806,"perc_r":null},{"com":4,"dt_com":20250609150000,"scheda":5,"enti_p":225,"enti_t":225,"perc":"25,54","vot_m":15187,"vot_f":17187,"vot_t":32374,"perc_r":null}]},{"tipo":"PROVINCIA","desc":"MESSINA","cod":48,"ele_m":232840,"ele_f":253525,"ele_t":486365,"com_vot":[{"com":1,"dt_com":20250608120000,"scheda":5,"enti_p":776,"enti_t":776,"perc":"4,41","vot_m":0,"vot_f":0,"vot_t":21459,"perc_r":null},{"com":2,"dt_com":20250608190000,"scheda":5,"enti_p":776,"enti_t":776,"perc":"10,55","vot_m":0,"vot_f":0,"vot_t":51335,"perc_r":null},{"com":3,"dt_com":20250608230000,"scheda":5,"enti_p":776,"enti_t":776,"perc":"16,34","vot_m":0,"vot_f":0,"vot_t":79470,"perc_r":null},{"com":4,"dt_com":20250609150000,"scheda":5,"enti_p":776,"enti_t":776,"perc":"23,25","vot_m":52112,"vot_f":60966,"vot_t":113078,"perc_r":null}]},{"tipo":"PROVINCIA","desc":"PALERMO","cod":55,"ele_m":463773,"ele_f":511109,"ele_t":974882,"com_vot":[{"com":1,"dt_com":20250608120000,"scheda":5,"enti_p":1186,"enti_t":1186,"perc":"5,06","vot_m":0,"vot_f":0,"vot_t":49332,"perc_r":null},{"com":2,"dt_com":20250608190000,"scheda":5,"enti_p":1186,"enti_t":1186,"perc":"12,38","vot_m":0,"vot_f":0,"vot_t":120674,"perc_r":null},{"com":3,"dt_com":20250608230000,"scheda":5,"enti_p":1186,"enti_t":1186,"perc":"18,07","vot_m":0,"vot_f":0,"vot_t":176175,"perc_r":null},{"com":4,"dt_com":20250609150000,"scheda":5,"enti_p":1186,"enti_t":1186,"perc":"24,87","vot_m":113005,"vot_f":129436,"vot_t":242441,"perc_r":null}]},{"tipo":"PROVINCIA","desc":"RAGUSA","cod":65,"ele_m":116067,"ele_f":123675,"ele_t":239742,"com_vot":[{"com":1,"dt_com":20250608120000,"scheda":5,"enti_p":310,"enti_t":310,"perc":"4,80","vot_m":0,"vot_f":0,"vot_t":11501,"perc_r":null},{"com":2,"dt_com":20250608190000,"scheda":5,"enti_p":310,"enti_t":310,"perc":"10,75","vot_m":0,"vot_f":0,"vot_t":25771,"perc_r":null},{"com":3,"dt_com":20250608230000,"scheda":5,"enti_p":310,"enti_t":310,"perc":"16,38","vot_m":0,"vot_f":0,"vot_t":39267,"perc_r":null},{"com":4,"dt_com":20250609150000,"scheda":5,"enti_p":310,"enti_t":310,"perc":"23,10","vot_m":25756,"vot_f":29633,"vot_t":55389,"perc_r":null}]},{"tipo":"PROVINCIA","desc":"SIRACUSA","cod":76,"ele_m":150717,"ele_f":159706,"ele_t":310423,"com_vot":[{"com":1,"dt_com":20250608120000,"scheda":5,"enti_p":422,"enti_t":422,"perc":"4,79","vot_m":0,"vot_f":0,"vot_t":14875,"perc_r":null},{"com":2,"dt_com":20250608190000,"scheda":5,"enti_p":422,"enti_t":422,"perc":"9,77","vot_m":0,"vot_f":0,"vot_t":30336,"perc_r":null},{"com":3,"dt_com":20250608230000,"scheda":5,"enti_p":422,"enti_t":422,"perc":"15,48","vot_m":0,"vot_f":0,"vot_t":48038,"perc_r":null},{"com":4,"dt_com":20250609150000,"scheda":5,"enti_p":422,"enti_t":422,"perc":"22,53","vot_m":33279,"vot_f":36671,"vot_t":69950,"perc_r":null}]},{"tipo":"PROVINCIA","desc":"TRAPANI","cod":82,"ele_m":159055,"ele_f":171075,"ele_t":330130,"com_vot":[{"com":1,"dt_com":20250608120000,"scheda":5,"enti_p":460,"enti_t":460,"perc":"3,61","vot_m":0,"vot_f":0,"vot_t":11930,"perc_r":null},{"com":2,"dt_com":20250608190000,"scheda":5,"enti_p":460,"enti_t":460,"perc":"9,08","vot_m":0,"vot_f":0,"vot_t":29972,"perc_r":null},{"com":3,"dt_com":20250608230000,"scheda":5,"enti_p":460,"enti_t":460,"perc":"13,85","vot_m":0,"vot_f":0,"vot_t":45721,"perc_r":null},{"com":4,"dt_com":20250609150000,"scheda":5,"enti_p":460,"enti_t":460,"perc":"20,29","vot_m":31453,"vot_f":35532,"vot_t":66985,"perc_r":null}]}]}}
