{"int":{"st":"ESERCIZIO","c_ele":9,"t_ele":"Referendum","f_elet":"VOTANTI","dt_ele":20250608000000,"l_terr":"COMUNE","area":"I","dt_agg":20250609154036},"note":null,"scheda":[{"cod":5,"desc":null}],"enti":{"ente_p":{"desc":"SAN DONATO DI LECCE","cod":680,"ele_m":2109,"ele_f":2398,"ele_t":4507,"com":[{"cod_reg":16,"com_att":4,"num_com":4}],"com_vot":[{"com":1,"dt_com":20250608120000,"enti_p":5,"enti_t":5,"perc":"4,70","vot_m":0,"vot_f":0,"vot_t":212,"perc_r":null},{"com":2,"dt_com":20250608190000,"enti_p":5,"enti_t":5,"perc":"9,39","vot_m":0,"vot_f":0,"vot_t":423,"perc_r":null},{"com":3,"dt_com":20250608230000,"enti_p":5,"enti_t":5,"perc":"17,66","vot_m":0,"vot_f":0,"vot_t":796,"perc_r":null},{"com":4,"dt_com":20250609150000,"enti_p":5,"enti_t":5,"perc":"25,92","vot_m":546,"vot_f":622,"vot_t":1168,"perc_r":null}]},"enti_f":[{"tipo":"SEZIONE","desc":"SEZIONE 1","cod":1,"osp":"N","ele_m":458,"ele_f":498,"ele_t":956,"com_vot":[{"com":1,"dt_com":20250608120000,"enti_p":1,"enti_t":1,"perc":"5,65","vot_m":0,"vot_f":0,"vot_t":54,"perc_r":null},{"com":2,"dt_com":20250608190000,"enti_p":1,"enti_t":1,"perc":"9,31","vot_m":0,"vot_f":0,"vot_t":89,"perc_r":null},{"com":3,"dt_com":20250608230000,"enti_p":1,"enti_t":1,"perc":"17,26","vot_m":0,"vot_f":0,"vot_t":165,"perc_r":null},{"com":4,"dt_com":20250609150000,"enti_p":1,"enti_t":1,"perc":"25,52","vot_m":114,"vot_f":130,"vot_t":244,"perc_r":null}]},{"tipo":"SEZIONE","desc":"SEZIONE 2","cod":2,"osp":"N","ele_m":406,"ele_f":470,"ele_t":876,"com_vot":[{"com":1,"dt_com":20250608120000,"enti_p":1,"enti_t":1,"perc":"4,22","vot_m":0,"vot_f":0,"vot_t":37,"perc_r":null},{"com":2,"dt_com":20250608190000,"enti_p":1,"enti_t":1,"perc":"8,79","vot_m":0,"vot_f":0,"vot_t":77,"perc_r":null},{"com":3,"dt_com":20250608230000,"enti_p":1,"enti_t":1,"perc":"16,44","vot_m":0,"vot_f":0,"vot_t":144,"perc_r":null},{"com":4,"dt_com":20250609150000,"enti_p":1,"enti_t":1,"perc":"23,17","vot_m":91,"vot_f":112,"vot_t":203,"perc_r":null}]},{"tipo":"SEZIONE","desc":"SEZIONE 3","cod":3,"osp":"N","ele_m":388,"ele_f":435,"ele_t":823,"com_vot":[{"com":1,"dt_com":20250608120000,"enti_p":1,"enti_t":1,"perc":"2,92","vot_m":0,"vot_f":0,"vot_t":24,"perc_r":null},{"com":2,"dt_com":20250608190000,"enti_p":1,"enti_t":1,"perc":"8,75","vot_m":0,"vot_f":0,"vot_t":72,"perc_r":null},{"com":3,"dt_com":20250608230000,"enti_p":1,"enti_t":1,"perc":"16,77","vot_m":0,"vot_f":0,"vot_t":138,"perc_r":null},{"com":4,"dt_com":20250609150000,"enti_p":1,"enti_t":1,"perc":"25,15","vot_m":99,"vot_f":108,"vot_t":207,"perc_r":null}]},{"tipo":"SEZIONE","desc":"SEZIONE 4","cod":4,"osp":"N","ele_m":469,"ele_f":523,"ele_t":992,"com_vot":[{"com":1,"dt_com":20250608120000,"enti_p":1,"enti_t":1,"perc":"5,65","vot_m":0,"vot_f":0,"vot_t":56,"perc_r":null},{"com":2,"dt_com":20250608190000,"enti_p":1,"enti_t":1,"perc":"9,48","vot_m":0,"vot_f":0,"vot_t":94,"perc_r":null},{"com":3,"dt_com":20250608230000,"enti_p":1,"enti_t":1,"perc":"17,14","vot_m":0,"vot_f":0,"vot_t":170,"perc_r":null},{"com":4,"dt_com":20250609150000,"enti_p":1,"enti_t":1,"perc":"24,19","vot_m":112,"vot_f":128,"vot_t":240,"perc_r":null}]},{"tipo":"SEZIONE","desc":"SEZIONE 5","cod":5,"osp":"N","ele_m":388,"ele_f":472,"ele_t":860,"com_vot":[{"com":1,"dt_com":20250608120000,"enti_p":1,"enti_t":1,"perc":"4,77","vot_m":0,"vot_f":0,"vot_t":41,"perc_r":null},{"com":2,"dt_com":20250608190000,"enti_p":1,"enti_t":1,"perc":"10,58","vot_m":0,"vot_f":0,"vot_t":91,"perc_r":null},{"com":3,"dt_com":20250608230000,"enti_p":1,"enti_t":1,"perc":"20,81","vot_m":0,"vot_f":0,"vot_t":179,"perc_r":null},{"com":4,"dt_com":20250609150000,"enti_p":1,"enti_t":1,"perc":"31,86","vot_m":130,"vot_f":144,"vot_t":274,"perc_r":null}]}]}}
