{"int":{"st":"ESERCIZIO","c_ele":9,"t_ele":"Referendum","f_elet":"VOTANTI","dt_ele":20250608000000,"l_terr":"COMUNE","area":"I","dt_agg":20250609150657},"note":null,"scheda":[{"cod":3,"desc":null}],"enti":{"ente_p":{"desc":"BELLEGRA","cod":120,"ele_m":1091,"ele_f":1131,"ele_t":2222,"com":[{"cod_reg":12,"com_att":4,"num_com":4}],"com_vot":[{"com":1,"dt_com":20250608120000,"enti_p":3,"enti_t":3,"perc":"4,86","vot_m":0,"vot_f":0,"vot_t":108,"perc_r":null},{"com":2,"dt_com":20250608190000,"enti_p":3,"enti_t":3,"perc":"15,03","vot_m":0,"vot_f":0,"vot_t":334,"perc_r":null},{"com":3,"dt_com":20250608230000,"enti_p":3,"enti_t":3,"perc":"21,65","vot_m":0,"vot_f":0,"vot_t":481,"perc_r":null},{"com":4,"dt_com":20250609150000,"enti_p":3,"enti_t":3,"perc":"29,66","vot_m":299,"vot_f":360,"vot_t":659,"perc_r":null}]},"enti_f":[{"tipo":"SEZIONE","desc":"SEZIONE 1","cod":1,"osp":"N","ele_m":414,"ele_f":428,"ele_t":842,"com_vot":[{"com":1,"dt_com":20250608120000,"enti_p":1,"enti_t":1,"perc":"4,39","vot_m":0,"vot_f":0,"vot_t":37,"perc_r":null},{"com":2,"dt_com":20250608190000,"enti_p":1,"enti_t":1,"perc":"15,44","vot_m":0,"vot_f":0,"vot_t":130,"perc_r":null},{"com":3,"dt_com":20250608230000,"enti_p":1,"enti_t":1,"perc":"22,21","vot_m":0,"vot_f":0,"vot_t":187,"perc_r":null},{"com":4,"dt_com":20250609150000,"enti_p":1,"enti_t":1,"perc":"29,93","vot_m":115,"vot_f":137,"vot_t":252,"perc_r":null}]},{"tipo":"SEZIONE","desc":"SEZIONE 2","cod":2,"osp":"N","ele_m":363,"ele_f":396,"ele_t":759,"com_vot":[{"com":1,"dt_com":20250608120000,"enti_p":1,"enti_t":1,"perc":"5,14","vot_m":0,"vot_f":0,"vot_t":39,"perc_r":null},{"com":2,"dt_com":20250608190000,"enti_p":1,"enti_t":1,"perc":"14,23","vot_m":0,"vot_f":0,"vot_t":108,"perc_r":null},{"com":3,"dt_com":20250608230000,"enti_p":1,"enti_t":1,"perc":"21,34","vot_m":0,"vot_f":0,"vot_t":162,"perc_r":null},{"com":4,"dt_com":20250609150000,"enti_p":1,"enti_t":1,"perc":"30,04","vot_m":101,"vot_f":127,"vot_t":228,"perc_r":null}]},{"tipo":"SEZIONE","desc":"SEZIONE 3","cod":3,"osp":"N","ele_m":314,"ele_f":307,"ele_t":621,"com_vot":[{"com":1,"dt_com":20250608120000,"enti_p":1,"enti_t":1,"perc":"5,15","vot_m":0,"vot_f":0,"vot_t":32,"perc_r":null},{"com":2,"dt_com":20250608190000,"enti_p":1,"enti_t":1,"perc":"15,46","vot_m":0,"vot_f":0,"vot_t":96,"perc_r":null},{"com":3,"dt_com":20250608230000,"enti_p":1,"enti_t":1,"perc":"21,26","vot_m":0,"vot_f":0,"vot_t":132,"perc_r":null},{"com":4,"dt_com":20250609150000,"enti_p":1,"enti_t":1,"perc":"28,82","vot_m":83,"vot_f":96,"vot_t":179,"perc_r":null}]}]}}
