{"int":{"st":"ESERCIZIO","c_ele":9,"t_ele":"Referendum","f_elet":"VOTANTI","dt_ele":20250608000000,"l_terr":"COMUNE","area":"I","dt_agg":20250609152020},"note":null,"scheda":[{"cod":3,"desc":null}],"enti":{"ente_p":{"desc":"VALDINA","cod":1010,"ele_m":508,"ele_f":519,"ele_t":1027,"com":[{"cod_reg":19,"com_att":4,"num_com":4}],"com_vot":[{"com":1,"dt_com":20250608120000,"enti_p":3,"enti_t":3,"perc":"3,99","vot_m":0,"vot_f":0,"vot_t":41,"perc_r":null},{"com":2,"dt_com":20250608190000,"enti_p":3,"enti_t":3,"perc":"9,74","vot_m":0,"vot_f":0,"vot_t":100,"perc_r":null},{"com":3,"dt_com":20250608230000,"enti_p":3,"enti_t":3,"perc":"16,36","vot_m":0,"vot_f":0,"vot_t":168,"perc_r":null},{"com":4,"dt_com":20250609150000,"enti_p":3,"enti_t":3,"perc":"22,98","vot_m":102,"vot_f":134,"vot_t":236,"perc_r":null}]},"enti_f":[{"tipo":"SEZIONE","desc":"SEZIONE 1","cod":1,"osp":"N","ele_m":134,"ele_f":141,"ele_t":275,"com_vot":[{"com":1,"dt_com":20250608120000,"enti_p":1,"enti_t":1,"perc":"3,27","vot_m":0,"vot_f":0,"vot_t":9,"perc_r":null},{"com":2,"dt_com":20250608190000,"enti_p":1,"enti_t":1,"perc":"8,36","vot_m":0,"vot_f":0,"vot_t":23,"perc_r":null},{"com":3,"dt_com":20250608230000,"enti_p":1,"enti_t":1,"perc":"17,45","vot_m":0,"vot_f":0,"vot_t":48,"perc_r":null},{"com":4,"dt_com":20250609150000,"enti_p":1,"enti_t":1,"perc":"23,64","vot_m":26,"vot_f":39,"vot_t":65,"perc_r":null}]},{"tipo":"SEZIONE","desc":"SEZIONE 2","cod":2,"osp":"N","ele_m":91,"ele_f":92,"ele_t":183,"com_vot":[{"com":1,"dt_com":20250608120000,"enti_p":1,"enti_t":1,"perc":"6,01","vot_m":0,"vot_f":0,"vot_t":11,"perc_r":null},{"com":2,"dt_com":20250608190000,"enti_p":1,"enti_t":1,"perc":"12,57","vot_m":0,"vot_f":0,"vot_t":23,"perc_r":null},{"com":3,"dt_com":20250608230000,"enti_p":1,"enti_t":1,"perc":"18,03","vot_m":0,"vot_f":0,"vot_t":33,"perc_r":null},{"com":4,"dt_com":20250609150000,"enti_p":1,"enti_t":1,"perc":"24,04","vot_m":17,"vot_f":27,"vot_t":44,"perc_r":null}]},{"tipo":"SEZIONE","desc":"SEZIONE 3","cod":3,"osp":"N","ele_m":283,"ele_f":286,"ele_t":569,"com_vot":[{"com":1,"dt_com":20250608120000,"enti_p":1,"enti_t":1,"perc":"3,69","vot_m":0,"vot_f":0,"vot_t":21,"perc_r":null},{"com":2,"dt_com":20250608190000,"enti_p":1,"enti_t":1,"perc":"9,49","vot_m":0,"vot_f":0,"vot_t":54,"perc_r":null},{"com":3,"dt_com":20250608230000,"enti_p":1,"enti_t":1,"perc":"15,29","vot_m":0,"vot_f":0,"vot_t":87,"perc_r":null},{"com":4,"dt_com":20250609150000,"enti_p":1,"enti_t":1,"perc":"22,32","vot_m":59,"vot_f":68,"vot_t":127,"perc_r":null}]}]}}
