{"int":{"st":"ESERCIZIO","c_ele":9,"t_ele":"Referendum","f_elet":"VOTANTI","dt_ele":20250608000000,"l_terr":"COMUNE","area":"I","dt_agg":20250609180934},"note":["LA SEZIONE OSPEDALIERA NON HA UN CORPO ELETTORALE PREDEFINITO E QUINDI L'AFFLUENZA AL VOTO NON PUO' ESSERE CALCOLATA IN VALORE PERCENTUALE"],"scheda":[{"cod":5,"desc":null}],"enti":{"ente_p":{"desc":"ALESSANDRIA","cod":30,"ele_m":31845,"ele_f":35138,"ele_t":66983,"com":[{"cod_reg":1,"com_att":4,"num_com":4}],"com_vot":[{"com":1,"dt_com":20250608120000,"enti_p":93,"enti_t":93,"perc":"7,48","vot_m":0,"vot_f":0,"vot_t":5009,"perc_r":null},{"com":2,"dt_com":20250608190000,"enti_p":93,"enti_t":93,"perc":"17,00","vot_m":0,"vot_f":0,"vot_t":11385,"perc_r":null},{"com":3,"dt_com":20250608230000,"enti_p":93,"enti_t":93,"perc":"23,68","vot_m":0,"vot_f":0,"vot_t":15864,"perc_r":null},{"com":4,"dt_com":20250609150000,"enti_p":93,"enti_t":93,"perc":"30,43","vot_m":9506,"vot_f":10879,"vot_t":20385,"perc_r":null}]},"enti_f":[{"tipo":"SEZIONE","desc":"SEZIONE 1","cod":1,"osp":"N","ele_m":260,"ele_f":288,"ele_t":548,"com_vot":[{"com":1,"dt_com":20250608120000,"enti_p":1,"enti_t":1,"perc":"5,84","vot_m":0,"vot_f":0,"vot_t":32,"perc_r":null},{"com":2,"dt_com":20250608190000,"enti_p":1,"enti_t":1,"perc":"14,60","vot_m":0,"vot_f":0,"vot_t":80,"perc_r":null},{"com":3,"dt_com":20250608230000,"enti_p":1,"enti_t":1,"perc":"19,53","vot_m":0,"vot_f":0,"vot_t":107,"perc_r":null},{"com":4,"dt_com":20250609150000,"enti_p":1,"enti_t":1,"perc":"25,36","vot_m":63,"vot_f":76,"vot_t":139,"perc_r":null}]},{"tipo":"SEZIONE","desc":"SEZIONE 2","cod":2,"osp":"N","ele_m":353,"ele_f":355,"ele_t":708,"com_vot":[{"com":1,"dt_com":20250608120000,"enti_p":1,"enti_t":1,"perc":"8,19","vot_m":0,"vot_f":0,"vot_t":58,"perc_r":null},{"com":2,"dt_com":20250608190000,"enti_p":1,"enti_t":1,"perc":"17,94","vot_m":0,"vot_f":0,"vot_t":127,"perc_r":null},{"com":3,"dt_com":20250608230000,"enti_p":1,"enti_t":1,"perc":"24,58","vot_m":0,"vot_f":0,"vot_t":174,"perc_r":null},{"com":4,"dt_com":20250609150000,"enti_p":1,"enti_t":1,"perc":"30,08","vot_m":104,"vot_f":109,"vot_t":213,"perc_r":null}]},{"tipo":"SEZIONE","desc":"SEZIONE 3","cod":3,"osp":"N","ele_m":334,"ele_f":387,"ele_t":721,"com_vot":[{"com":1,"dt_com":20250608120000,"enti_p":1,"enti_t":1,"perc":"9,99","vot_m":0,"vot_f":0,"vot_t":72,"perc_r":null},{"com":2,"dt_com":20250608190000,"enti_p":1,"enti_t":1,"perc":"21,36","vot_m":0,"vot_f":0,"vot_t":154,"perc_r":null},{"com":3,"dt_com":20250608230000,"enti_p":1,"enti_t":1,"perc":"27,18","vot_m":0,"vot_f":0,"vot_t":196,"perc_r":null},{"com":4,"dt_com":20250609150000,"enti_p":1,"enti_t":1,"perc":"33,98","vot_m":111,"vot_f":134,"vot_t":245,"perc_r":null}]},{"tipo":"SEZIONE","desc":"SEZIONE 4","cod":4,"osp":"N","ele_m":308,"ele_f":341,"ele_t":649,"com_vot":[{"com":1,"dt_com":20250608120000,"enti_p":1,"enti_t":1,"perc":"7,55","vot_m":0,"vot_f":0,"vot_t":49,"perc_r":null},{"com":2,"dt_com":20250608190000,"enti_p":1,"enti_t":1,"perc":"18,49","vot_m":0,"vot_f":0,"vot_t":120,"perc_r":null},{"com":3,"dt_com":20250608230000,"enti_p":1,"enti_t":1,"perc":"22,96","vot_m":0,"vot_f":0,"vot_t":149,"perc_r":null},{"com":4,"dt_com":20250609150000,"enti_p":1,"enti_t":1,"perc":"30,35","vot_m":93,"vot_f":104,"vot_t":197,"perc_r":null}]},{"tipo":"SEZIONE","desc":"SEZIONE 5","cod":5,"osp":"N","ele_m":356,"ele_f":409,"ele_t":765,"com_vot":[{"com":1,"dt_com":20250608120000,"enti_p":1,"enti_t":1,"perc":"8,24","vot_m":0,"vot_f":0,"vot_t":63,"perc_r":null},{"com":2,"dt_com":20250608190000,"enti_p":1,"enti_t":1,"perc":"17,91","vot_m":0,"vot_f":0,"vot_t":137,"perc_r":null},{"com":3,"dt_com":20250608230000,"enti_p":1,"enti_t":1,"perc":"25,36","vot_m":0,"vot_f":0,"vot_t":194,"perc_r":null},{"com":4,"dt_com":20250609150000,"enti_p":1,"enti_t":1,"perc":"32,16","vot_m":116,"vot_f":130,"vot_t":246,"perc_r":null}]},{"tipo":"SEZIONE","desc":"SEZIONE 6","cod":6,"osp":"N","ele_m":340,"ele_f":359,"ele_t":699,"com_vot":[{"com":1,"dt_com":20250608120000,"enti_p":1,"enti_t":1,"perc":"8,15","vot_m":0,"vot_f":0,"vot_t":57,"perc_r":null},{"com":2,"dt_com":20250608190000,"enti_p":1,"enti_t":1,"perc":"17,31","vot_m":0,"vot_f":0,"vot_t":121,"perc_r":null},{"com":3,"dt_com":20250608230000,"enti_p":1,"enti_t":1,"perc":"23,03","vot_m":0,"vot_f":0,"vot_t":161,"perc_r":null},{"com":4,"dt_com":20250609150000,"enti_p":1,"enti_t":1,"perc":"31,04","vot_m":101,"vot_f":116,"vot_t":217,"perc_r":null}]},{"tipo":"SEZIONE","desc":"SEZIONE 7","cod":7,"osp":"N","ele_m":300,"ele_f":341,"ele_t":641,"com_vot":[{"com":1,"dt_com":20250608120000,"enti_p":1,"enti_t":1,"perc":"8,74","vot_m":0,"vot_f":0,"vot_t":56,"perc_r":null},{"com":2,"dt_com":20250608190000,"enti_p":1,"enti_t":1,"perc":"20,90","vot_m":0,"vot_f":0,"vot_t":134,"perc_r":null},{"com":3,"dt_com":20250608230000,"enti_p":1,"enti_t":1,"perc":"28,24","vot_m":0,"vot_f":0,"vot_t":181,"perc_r":null},{"com":4,"dt_com":20250609150000,"enti_p":1,"enti_t":1,"perc":"36,19","vot_m":111,"vot_f":121,"vot_t":232,"perc_r":null}]},{"tipo":"SEZIONE","desc":"SEZIONE 8","cod":8,"osp":"N","ele_m":304,"ele_f":367,"ele_t":671,"com_vot":[{"com":1,"dt_com":20250608120000,"enti_p":1,"enti_t":1,"perc":"8,94","vot_m":0,"vot_f":0,"vot_t":60,"perc_r":null},{"com":2,"dt_com":20250608190000,"enti_p":1,"enti_t":1,"perc":"18,78","vot_m":0,"vot_f":0,"vot_t":126,"perc_r":null},{"com":3,"dt_com":20250608230000,"enti_p":1,"enti_t":1,"perc":"26,83","vot_m":0,"vot_f":0,"vot_t":180,"perc_r":null},{"com":4,"dt_com":20250609150000,"enti_p":1,"enti_t":1,"perc":"34,13","vot_m":105,"vot_f":124,"vot_t":229,"perc_r":null}]},{"tipo":"SEZIONE","desc":"SEZIONE 9","cod":9,"osp":"N","ele_m":299,"ele_f":352,"ele_t":651,"com_vot":[{"com":1,"dt_com":20250608120000,"enti_p":1,"enti_t":1,"perc":"7,22","vot_m":0,"vot_f":0,"vot_t":47,"perc_r":null},{"com":2,"dt_com":20250608190000,"enti_p":1,"enti_t":1,"perc":"19,35","vot_m":0,"vot_f":0,"vot_t":126,"perc_r":null},{"com":3,"dt_com":20250608230000,"enti_p":1,"enti_t":1,"perc":"25,50","vot_m":0,"vot_f":0,"vot_t":166,"perc_r":null},{"com":4,"dt_com":20250609150000,"enti_p":1,"enti_t":1,"perc":"30,88","vot_m":91,"vot_f":110,"vot_t":201,"perc_r":null}]},{"tipo":"SEZIONE","desc":"SEZIONE 10","cod":10,"osp":"N","ele_m":316,"ele_f":376,"ele_t":692,"com_vot":[{"com":1,"dt_com":20250608120000,"enti_p":1,"enti_t":1,"perc":"7,37","vot_m":0,"vot_f":0,"vot_t":51,"perc_r":null},{"com":2,"dt_com":20250608190000,"enti_p":1,"enti_t":1,"perc":"17,63","vot_m":0,"vot_f":0,"vot_t":122,"perc_r":null},{"com":3,"dt_com":20250608230000,"enti_p":1,"enti_t":1,"perc":"26,16","vot_m":0,"vot_f":0,"vot_t":181,"perc_r":null},{"com":4,"dt_com":20250609150000,"enti_p":1,"enti_t":1,"perc":"33,53","vot_m":108,"vot_f":124,"vot_t":232,"perc_r":null}]},{"tipo":"SEZIONE","desc":"SEZIONE 11","cod":11,"osp":"N","ele_m":305,"ele_f":361,"ele_t":666,"com_vot":[{"com":1,"dt_com":20250608120000,"enti_p":1,"enti_t":1,"perc":"7,51","vot_m":0,"vot_f":0,"vot_t":50,"perc_r":null},{"com":2,"dt_com":20250608190000,"enti_p":1,"enti_t":1,"perc":"16,07","vot_m":0,"vot_f":0,"vot_t":107,"perc_r":null},{"com":3,"dt_com":20250608230000,"enti_p":1,"enti_t":1,"perc":"20,87","vot_m":0,"vot_f":0,"vot_t":139,"perc_r":null},{"com":4,"dt_com":20250609150000,"enti_p":1,"enti_t":1,"perc":"28,08","vot_m":78,"vot_f":109,"vot_t":187,"perc_r":null}]},{"tipo":"SEZIONE","desc":"SEZIONE 12","cod":12,"osp":"N","ele_m":328,"ele_f":347,"ele_t":675,"com_vot":[{"com":1,"dt_com":20250608120000,"enti_p":1,"enti_t":1,"perc":"7,11","vot_m":0,"vot_f":0,"vot_t":48,"perc_r":null},{"com":2,"dt_com":20250608190000,"enti_p":1,"enti_t":1,"perc":"15,26","vot_m":0,"vot_f":0,"vot_t":103,"perc_r":null},{"com":3,"dt_com":20250608230000,"enti_p":1,"enti_t":1,"perc":"22,22","vot_m":0,"vot_f":0,"vot_t":150,"perc_r":null},{"com":4,"dt_com":20250609150000,"enti_p":1,"enti_t":1,"perc":"28,44","vot_m":96,"vot_f":96,"vot_t":192,"perc_r":null}]},{"tipo":"SEZIONE","desc":"SEZIONE 13","cod":13,"osp":"N","ele_m":313,"ele_f":372,"ele_t":685,"com_vot":[{"com":1,"dt_com":20250608120000,"enti_p":1,"enti_t":1,"perc":"9,05","vot_m":0,"vot_f":0,"vot_t":62,"perc_r":null},{"com":2,"dt_com":20250608190000,"enti_p":1,"enti_t":1,"perc":"20,29","vot_m":0,"vot_f":0,"vot_t":139,"perc_r":null},{"com":3,"dt_com":20250608230000,"enti_p":1,"enti_t":1,"perc":"27,45","vot_m":0,"vot_f":0,"vot_t":188,"perc_r":null},{"com":4,"dt_com":20250609150000,"enti_p":1,"enti_t":1,"perc":"34,01","vot_m":102,"vot_f":131,"vot_t":233,"perc_r":null}]},{"tipo":"SEZIONE","desc":"SEZIONE 14","cod":14,"osp":"N","ele_m":332,"ele_f":346,"ele_t":678,"com_vot":[{"com":1,"dt_com":20250608120000,"enti_p":1,"enti_t":1,"perc":"8,41","vot_m":0,"vot_f":0,"vot_t":57,"perc_r":null},{"com":2,"dt_com":20250608190000,"enti_p":1,"enti_t":1,"perc":"19,62","vot_m":0,"vot_f":0,"vot_t":133,"perc_r":null},{"com":3,"dt_com":20250608230000,"enti_p":1,"enti_t":1,"perc":"25,52","vot_m":0,"vot_f":0,"vot_t":173,"perc_r":null},{"com":4,"dt_com":20250609150000,"enti_p":1,"enti_t":1,"perc":"32,60","vot_m":95,"vot_f":126,"vot_t":221,"perc_r":null}]},{"tipo":"SEZIONE","desc":"SEZIONE 15","cod":15,"osp":"N","ele_m":281,"ele_f":343,"ele_t":624,"com_vot":[{"com":1,"dt_com":20250608120000,"enti_p":1,"enti_t":1,"perc":"8,01","vot_m":0,"vot_f":0,"vot_t":50,"perc_r":null},{"com":2,"dt_com":20250608190000,"enti_p":1,"enti_t":1,"perc":"17,31","vot_m":0,"vot_f":0,"vot_t":108,"perc_r":null},{"com":3,"dt_com":20250608230000,"enti_p":1,"enti_t":1,"perc":"27,08","vot_m":0,"vot_f":0,"vot_t":169,"perc_r":null},{"com":4,"dt_com":20250609150000,"enti_p":1,"enti_t":1,"perc":"31,73","vot_m":89,"vot_f":109,"vot_t":198,"perc_r":null}]},{"tipo":"SEZIONE","desc":"SEZIONE 16","cod":16,"osp":"N","ele_m":326,"ele_f":418,"ele_t":744,"com_vot":[{"com":1,"dt_com":20250608120000,"enti_p":1,"enti_t":1,"perc":"7,26","vot_m":0,"vot_f":0,"vot_t":54,"perc_r":null},{"com":2,"dt_com":20250608190000,"enti_p":1,"enti_t":1,"perc":"16,53","vot_m":0,"vot_f":0,"vot_t":123,"perc_r":null},{"com":3,"dt_com":20250608230000,"enti_p":1,"enti_t":1,"perc":"22,45","vot_m":0,"vot_f":0,"vot_t":167,"perc_r":null},{"com":4,"dt_com":20250609150000,"enti_p":1,"enti_t":1,"perc":"31,32","vot_m":106,"vot_f":127,"vot_t":233,"perc_r":null}]},{"tipo":"SEZIONE","desc":"SEZIONE 17","cod":17,"osp":"N","ele_m":342,"ele_f":405,"ele_t":747,"com_vot":[{"com":1,"dt_com":20250608120000,"enti_p":1,"enti_t":1,"perc":"10,04","vot_m":0,"vot_f":0,"vot_t":75,"perc_r":null},{"com":2,"dt_com":20250608190000,"enti_p":1,"enti_t":1,"perc":"18,47","vot_m":0,"vot_f":0,"vot_t":138,"perc_r":null},{"com":3,"dt_com":20250608230000,"enti_p":1,"enti_t":1,"perc":"26,37","vot_m":0,"vot_f":0,"vot_t":197,"perc_r":null},{"com":4,"dt_com":20250609150000,"enti_p":1,"enti_t":1,"perc":"34,27","vot_m":112,"vot_f":144,"vot_t":256,"perc_r":null}]},{"tipo":"SEZIONE","desc":"SEZIONE 18","cod":18,"osp":"N","ele_m":330,"ele_f":406,"ele_t":736,"com_vot":[{"com":1,"dt_com":20250608120000,"enti_p":1,"enti_t":1,"perc":"6,52","vot_m":0,"vot_f":0,"vot_t":48,"perc_r":null},{"com":2,"dt_com":20250608190000,"enti_p":1,"enti_t":1,"perc":"17,26","vot_m":0,"vot_f":0,"vot_t":127,"perc_r":null},{"com":3,"dt_com":20250608230000,"enti_p":1,"enti_t":1,"perc":"24,46","vot_m":0,"vot_f":0,"vot_t":180,"perc_r":null},{"com":4,"dt_com":20250609150000,"enti_p":1,"enti_t":1,"perc":"32,74","vot_m":106,"vot_f":135,"vot_t":241,"perc_r":null}]},{"tipo":"SEZIONE","desc":"SEZIONE 19","cod":19,"osp":"N","ele_m":313,"ele_f":408,"ele_t":721,"com_vot":[{"com":1,"dt_com":20250608120000,"enti_p":1,"enti_t":1,"perc":"8,04","vot_m":0,"vot_f":0,"vot_t":58,"perc_r":null},{"com":2,"dt_com":20250608190000,"enti_p":1,"enti_t":1,"perc":"19,00","vot_m":0,"vot_f":0,"vot_t":137,"perc_r":null},{"com":3,"dt_com":20250608230000,"enti_p":1,"enti_t":1,"perc":"28,16","vot_m":0,"vot_f":0,"vot_t":203,"perc_r":null},{"com":4,"dt_com":20250609150000,"enti_p":1,"enti_t":1,"perc":"35,51","vot_m":111,"vot_f":145,"vot_t":256,"perc_r":null}]},{"tipo":"SEZIONE","desc":"SEZIONE 20","cod":20,"osp":"N","ele_m":310,"ele_f":385,"ele_t":695,"com_vot":[{"com":1,"dt_com":20250608120000,"enti_p":1,"enti_t":1,"perc":"8,20","vot_m":0,"vot_f":0,"vot_t":57,"perc_r":null},{"com":2,"dt_com":20250608190000,"enti_p":1,"enti_t":1,"perc":"17,84","vot_m":0,"vot_f":0,"vot_t":124,"perc_r":null},{"com":3,"dt_com":20250608230000,"enti_p":1,"enti_t":1,"perc":"25,47","vot_m":0,"vot_f":0,"vot_t":177,"perc_r":null},{"com":4,"dt_com":20250609150000,"enti_p":1,"enti_t":1,"perc":"33,38","vot_m":98,"vot_f":134,"vot_t":232,"perc_r":null}]},{"tipo":"SEZIONE","desc":"SEZIONE 21","cod":21,"osp":"N","ele_m":307,"ele_f":311,"ele_t":618,"com_vot":[{"com":1,"dt_com":20250608120000,"enti_p":1,"enti_t":1,"perc":"7,12","vot_m":0,"vot_f":0,"vot_t":44,"perc_r":null},{"com":2,"dt_com":20250608190000,"enti_p":1,"enti_t":1,"perc":"17,64","vot_m":0,"vot_f":0,"vot_t":109,"perc_r":null},{"com":3,"dt_com":20250608230000,"enti_p":1,"enti_t":1,"perc":"22,98","vot_m":0,"vot_f":0,"vot_t":142,"perc_r":null},{"com":4,"dt_com":20250609150000,"enti_p":1,"enti_t":1,"perc":"31,07","vot_m":94,"vot_f":98,"vot_t":192,"perc_r":null}]},{"tipo":"SEZIONE","desc":"SEZIONE 22","cod":22,"osp":"N","ele_m":338,"ele_f":395,"ele_t":733,"com_vot":[{"com":1,"dt_com":20250608120000,"enti_p":1,"enti_t":1,"perc":"7,64","vot_m":0,"vot_f":0,"vot_t":56,"perc_r":null},{"com":2,"dt_com":20250608190000,"enti_p":1,"enti_t":1,"perc":"18,14","vot_m":0,"vot_f":0,"vot_t":133,"perc_r":null},{"com":3,"dt_com":20250608230000,"enti_p":1,"enti_t":1,"perc":"23,06","vot_m":0,"vot_f":0,"vot_t":169,"perc_r":null},{"com":4,"dt_com":20250609150000,"enti_p":1,"enti_t":1,"perc":"29,47","vot_m":91,"vot_f":125,"vot_t":216,"perc_r":null}]},{"tipo":"SEZIONE","desc":"SEZIONE 23","cod":23,"osp":"N","ele_m":344,"ele_f":371,"ele_t":715,"com_vot":[{"com":1,"dt_com":20250608120000,"enti_p":1,"enti_t":1,"perc":"6,71","vot_m":0,"vot_f":0,"vot_t":48,"perc_r":null},{"com":2,"dt_com":20250608190000,"enti_p":1,"enti_t":1,"perc":"15,94","vot_m":0,"vot_f":0,"vot_t":114,"perc_r":null},{"com":3,"dt_com":20250608230000,"enti_p":1,"enti_t":1,"perc":"22,38","vot_m":0,"vot_f":0,"vot_t":160,"perc_r":null},{"com":4,"dt_com":20250609150000,"enti_p":1,"enti_t":1,"perc":"29,37","vot_m":97,"vot_f":113,"vot_t":210,"perc_r":null}]},{"tipo":"SEZIONE","desc":"SEZIONE 24","cod":24,"osp":"N","ele_m":296,"ele_f":358,"ele_t":654,"com_vot":[{"com":1,"dt_com":20250608120000,"enti_p":1,"enti_t":1,"perc":"7,80","vot_m":0,"vot_f":0,"vot_t":51,"perc_r":null},{"com":2,"dt_com":20250608190000,"enti_p":1,"enti_t":1,"perc":"22,94","vot_m":0,"vot_f":0,"vot_t":150,"perc_r":null},{"com":3,"dt_com":20250608230000,"enti_p":1,"enti_t":1,"perc":"33,33","vot_m":0,"vot_f":0,"vot_t":218,"perc_r":null},{"com":4,"dt_com":20250609150000,"enti_p":1,"enti_t":1,"perc":"38,07","vot_m":131,"vot_f":118,"vot_t":249,"perc_r":null}]},{"tipo":"SEZIONE","desc":"SEZIONE 25","cod":25,"osp":"N","ele_m":321,"ele_f":388,"ele_t":709,"com_vot":[{"com":1,"dt_com":20250608120000,"enti_p":1,"enti_t":1,"perc":"12,41","vot_m":0,"vot_f":0,"vot_t":88,"perc_r":null},{"com":2,"dt_com":20250608190000,"enti_p":1,"enti_t":1,"perc":"27,93","vot_m":0,"vot_f":0,"vot_t":198,"perc_r":null},{"com":3,"dt_com":20250608230000,"enti_p":1,"enti_t":1,"perc":"36,53","vot_m":0,"vot_f":0,"vot_t":259,"perc_r":null},{"com":4,"dt_com":20250609150000,"enti_p":1,"enti_t":1,"perc":"42,88","vot_m":138,"vot_f":166,"vot_t":304,"perc_r":null}]},{"tipo":"SEZIONE","desc":"SEZIONE 26","cod":26,"osp":"N","ele_m":307,"ele_f":309,"ele_t":616,"com_vot":[{"com":1,"dt_com":20250608120000,"enti_p":1,"enti_t":1,"perc":"8,12","vot_m":0,"vot_f":0,"vot_t":50,"perc_r":null},{"com":2,"dt_com":20250608190000,"enti_p":1,"enti_t":1,"perc":"20,62","vot_m":0,"vot_f":0,"vot_t":127,"perc_r":null},{"com":3,"dt_com":20250608230000,"enti_p":1,"enti_t":1,"perc":"26,95","vot_m":0,"vot_f":0,"vot_t":166,"perc_r":null},{"com":4,"dt_com":20250609150000,"enti_p":1,"enti_t":1,"perc":"33,28","vot_m":101,"vot_f":104,"vot_t":205,"perc_r":null}]},{"tipo":"SEZIONE","desc":"SEZIONE 27","cod":27,"osp":"N","ele_m":346,"ele_f":399,"ele_t":745,"com_vot":[{"com":1,"dt_com":20250608120000,"enti_p":1,"enti_t":1,"perc":"6,98","vot_m":0,"vot_f":0,"vot_t":52,"perc_r":null},{"com":2,"dt_com":20250608190000,"enti_p":1,"enti_t":1,"perc":"17,05","vot_m":0,"vot_f":0,"vot_t":127,"perc_r":null},{"com":3,"dt_com":20250608230000,"enti_p":1,"enti_t":1,"perc":"23,22","vot_m":0,"vot_f":0,"vot_t":173,"perc_r":null},{"com":4,"dt_com":20250609150000,"enti_p":1,"enti_t":1,"perc":"30,74","vot_m":102,"vot_f":127,"vot_t":229,"perc_r":null}]},{"tipo":"SEZIONE","desc":"SEZIONE 28","cod":28,"osp":"N","ele_m":343,"ele_f":357,"ele_t":700,"com_vot":[{"com":1,"dt_com":20250608120000,"enti_p":1,"enti_t":1,"perc":"9,86","vot_m":0,"vot_f":0,"vot_t":69,"perc_r":null},{"com":2,"dt_com":20250608190000,"enti_p":1,"enti_t":1,"perc":"19,71","vot_m":0,"vot_f":0,"vot_t":138,"perc_r":null},{"com":3,"dt_com":20250608230000,"enti_p":1,"enti_t":1,"perc":"26,14","vot_m":0,"vot_f":0,"vot_t":183,"perc_r":null},{"com":4,"dt_com":20250609150000,"enti_p":1,"enti_t":1,"perc":"33,14","vot_m":113,"vot_f":119,"vot_t":232,"perc_r":null}]},{"tipo":"SEZIONE","desc":"SEZIONE 29","cod":29,"osp":"N","ele_m":260,"ele_f":343,"ele_t":603,"com_vot":[{"com":1,"dt_com":20250608120000,"enti_p":1,"enti_t":1,"perc":"4,98","vot_m":0,"vot_f":0,"vot_t":30,"perc_r":null},{"com":2,"dt_com":20250608190000,"enti_p":1,"enti_t":1,"perc":"14,76","vot_m":0,"vot_f":0,"vot_t":89,"perc_r":null},{"com":3,"dt_com":20250608230000,"enti_p":1,"enti_t":1,"perc":"20,56","vot_m":0,"vot_f":0,"vot_t":124,"perc_r":null},{"com":4,"dt_com":20250609150000,"enti_p":1,"enti_t":1,"perc":"26,70","vot_m":67,"vot_f":94,"vot_t":161,"perc_r":null}]},{"tipo":"SEZIONE","desc":"SEZIONE 30","cod":30,"osp":"N","ele_m":352,"ele_f":391,"ele_t":743,"com_vot":[{"com":1,"dt_com":20250608120000,"enti_p":1,"enti_t":1,"perc":"9,42","vot_m":0,"vot_f":0,"vot_t":70,"perc_r":null},{"com":2,"dt_com":20250608190000,"enti_p":1,"enti_t":1,"perc":"18,17","vot_m":0,"vot_f":0,"vot_t":135,"perc_r":null},{"com":3,"dt_com":20250608230000,"enti_p":1,"enti_t":1,"perc":"23,42","vot_m":0,"vot_f":0,"vot_t":174,"perc_r":null},{"com":4,"dt_com":20250609150000,"enti_p":1,"enti_t":1,"perc":"32,03","vot_m":115,"vot_f":123,"vot_t":238,"perc_r":null}]},{"tipo":"SEZIONE","desc":"SEZIONE 31","cod":31,"osp":"N","ele_m":490,"ele_f":387,"ele_t":877,"com_vot":[{"com":1,"dt_com":20250608120000,"enti_p":1,"enti_t":1,"perc":"7,18","vot_m":0,"vot_f":0,"vot_t":63,"perc_r":null},{"com":2,"dt_com":20250608190000,"enti_p":1,"enti_t":1,"perc":"15,28","vot_m":0,"vot_f":0,"vot_t":134,"perc_r":null},{"com":3,"dt_com":20250608230000,"enti_p":1,"enti_t":1,"perc":"19,38","vot_m":0,"vot_f":0,"vot_t":170,"perc_r":null},{"com":4,"dt_com":20250609150000,"enti_p":1,"enti_t":1,"perc":"24,63","vot_m":97,"vot_f":119,"vot_t":216,"perc_r":null}]},{"tipo":"SEZIONE","desc":"SEZIONE 32","cod":32,"osp":"N","ele_m":323,"ele_f":398,"ele_t":721,"com_vot":[{"com":1,"dt_com":20250608120000,"enti_p":1,"enti_t":1,"perc":"8,04","vot_m":0,"vot_f":0,"vot_t":58,"perc_r":null},{"com":2,"dt_com":20250608190000,"enti_p":1,"enti_t":1,"perc":"18,72","vot_m":0,"vot_f":0,"vot_t":135,"perc_r":null},{"com":3,"dt_com":20250608230000,"enti_p":1,"enti_t":1,"perc":"27,74","vot_m":0,"vot_f":0,"vot_t":200,"perc_r":null},{"com":4,"dt_com":20250609150000,"enti_p":1,"enti_t":1,"perc":"32,59","vot_m":111,"vot_f":124,"vot_t":235,"perc_r":null}]},{"tipo":"SEZIONE","desc":"SEZIONE 33","cod":33,"osp":"N","ele_m":257,"ele_f":347,"ele_t":604,"com_vot":[{"com":1,"dt_com":20250608120000,"enti_p":1,"enti_t":1,"perc":"4,97","vot_m":0,"vot_f":0,"vot_t":30,"perc_r":null},{"com":2,"dt_com":20250608190000,"enti_p":1,"enti_t":1,"perc":"13,25","vot_m":0,"vot_f":0,"vot_t":80,"perc_r":null},{"com":3,"dt_com":20250608230000,"enti_p":1,"enti_t":1,"perc":"17,22","vot_m":0,"vot_f":0,"vot_t":104,"perc_r":null},{"com":4,"dt_com":20250609150000,"enti_p":1,"enti_t":1,"perc":"23,68","vot_m":57,"vot_f":86,"vot_t":143,"perc_r":null}]},{"tipo":"SEZIONE","desc":"SEZIONE 34","cod":34,"osp":"N","ele_m":330,"ele_f":334,"ele_t":664,"com_vot":[{"com":1,"dt_com":20250608120000,"enti_p":1,"enti_t":1,"perc":"7,38","vot_m":0,"vot_f":0,"vot_t":49,"perc_r":null},{"com":2,"dt_com":20250608190000,"enti_p":1,"enti_t":1,"perc":"18,67","vot_m":0,"vot_f":0,"vot_t":124,"perc_r":null},{"com":3,"dt_com":20250608230000,"enti_p":1,"enti_t":1,"perc":"27,86","vot_m":0,"vot_f":0,"vot_t":185,"perc_r":null},{"com":4,"dt_com":20250609150000,"enti_p":1,"enti_t":1,"perc":"31,63","vot_m":100,"vot_f":110,"vot_t":210,"perc_r":null}]},{"tipo":"SEZIONE","desc":"SEZIONE 35","cod":35,"osp":"S","ele_m":0,"ele_f":0,"ele_t":0,"com_vot":[{"com":1,"dt_com":20250608120000,"enti_p":1,"enti_t":1,"perc":"0","vot_m":0,"vot_f":0,"vot_t":17,"perc_r":null},{"com":2,"dt_com":20250608190000,"enti_p":1,"enti_t":1,"perc":"0","vot_m":0,"vot_f":0,"vot_t":24,"perc_r":null},{"com":3,"dt_com":20250608230000,"enti_p":1,"enti_t":1,"perc":"0","vot_m":0,"vot_f":0,"vot_t":33,"perc_r":null},{"com":4,"dt_com":20250609150000,"enti_p":1,"enti_t":1,"perc":"0","vot_m":20,"vot_f":31,"vot_t":51,"perc_r":null}]},{"tipo":"SEZIONE","desc":"SEZIONE 36","cod":36,"osp":"N","ele_m":398,"ele_f":435,"ele_t":833,"com_vot":[{"com":1,"dt_com":20250608120000,"enti_p":1,"enti_t":1,"perc":"6,96","vot_m":0,"vot_f":0,"vot_t":58,"perc_r":null},{"com":2,"dt_com":20250608190000,"enti_p":1,"enti_t":1,"perc":"16,69","vot_m":0,"vot_f":0,"vot_t":139,"perc_r":null},{"com":3,"dt_com":20250608230000,"enti_p":1,"enti_t":1,"perc":"21,85","vot_m":0,"vot_f":0,"vot_t":182,"perc_r":null},{"com":4,"dt_com":20250609150000,"enti_p":1,"enti_t":1,"perc":"27,97","vot_m":104,"vot_f":129,"vot_t":233,"perc_r":null}]},{"tipo":"SEZIONE","desc":"SEZIONE 37","cod":37,"osp":"N","ele_m":331,"ele_f":361,"ele_t":692,"com_vot":[{"com":1,"dt_com":20250608120000,"enti_p":1,"enti_t":1,"perc":"11,71","vot_m":0,"vot_f":0,"vot_t":81,"perc_r":null},{"com":2,"dt_com":20250608190000,"enti_p":1,"enti_t":1,"perc":"22,11","vot_m":0,"vot_f":0,"vot_t":153,"perc_r":null},{"com":3,"dt_com":20250608230000,"enti_p":1,"enti_t":1,"perc":"29,91","vot_m":0,"vot_f":0,"vot_t":207,"perc_r":null},{"com":4,"dt_com":20250609150000,"enti_p":1,"enti_t":1,"perc":"35,26","vot_m":113,"vot_f":131,"vot_t":244,"perc_r":null}]},{"tipo":"SEZIONE","desc":"SEZIONE 38","cod":38,"osp":"N","ele_m":364,"ele_f":382,"ele_t":746,"com_vot":[{"com":1,"dt_com":20250608120000,"enti_p":1,"enti_t":1,"perc":"8,85","vot_m":0,"vot_f":0,"vot_t":66,"perc_r":null},{"com":2,"dt_com":20250608190000,"enti_p":1,"enti_t":1,"perc":"17,56","vot_m":0,"vot_f":0,"vot_t":131,"perc_r":null},{"com":3,"dt_com":20250608230000,"enti_p":1,"enti_t":1,"perc":"24,80","vot_m":0,"vot_f":0,"vot_t":185,"perc_r":null},{"com":4,"dt_com":20250609150000,"enti_p":1,"enti_t":1,"perc":"32,44","vot_m":107,"vot_f":135,"vot_t":242,"perc_r":null}]},{"tipo":"SEZIONE","desc":"SEZIONE 39","cod":39,"osp":"N","ele_m":292,"ele_f":420,"ele_t":712,"com_vot":[{"com":1,"dt_com":20250608120000,"enti_p":1,"enti_t":1,"perc":"6,88","vot_m":0,"vot_f":0,"vot_t":49,"perc_r":null},{"com":2,"dt_com":20250608190000,"enti_p":1,"enti_t":1,"perc":"17,70","vot_m":0,"vot_f":0,"vot_t":126,"perc_r":null},{"com":3,"dt_com":20250608230000,"enti_p":1,"enti_t":1,"perc":"23,46","vot_m":0,"vot_f":0,"vot_t":167,"perc_r":null},{"com":4,"dt_com":20250609150000,"enti_p":1,"enti_t":1,"perc":"33,29","vot_m":96,"vot_f":141,"vot_t":237,"perc_r":null}]},{"tipo":"SEZIONE","desc":"SEZIONE 40","cod":40,"osp":"N","ele_m":304,"ele_f":379,"ele_t":683,"com_vot":[{"com":1,"dt_com":20250608120000,"enti_p":1,"enti_t":1,"perc":"12,30","vot_m":0,"vot_f":0,"vot_t":84,"perc_r":null},{"com":2,"dt_com":20250608190000,"enti_p":1,"enti_t":1,"perc":"23,57","vot_m":0,"vot_f":0,"vot_t":161,"perc_r":null},{"com":3,"dt_com":20250608230000,"enti_p":1,"enti_t":1,"perc":"31,33","vot_m":0,"vot_f":0,"vot_t":214,"perc_r":null},{"com":4,"dt_com":20250609150000,"enti_p":1,"enti_t":1,"perc":"38,07","vot_m":113,"vot_f":147,"vot_t":260,"perc_r":null}]},{"tipo":"SEZIONE","desc":"SEZIONE 41","cod":41,"osp":"N","ele_m":377,"ele_f":427,"ele_t":804,"com_vot":[{"com":1,"dt_com":20250608120000,"enti_p":1,"enti_t":1,"perc":"6,22","vot_m":0,"vot_f":0,"vot_t":50,"perc_r":null},{"com":2,"dt_com":20250608190000,"enti_p":1,"enti_t":1,"perc":"17,04","vot_m":0,"vot_f":0,"vot_t":137,"perc_r":null},{"com":3,"dt_com":20250608230000,"enti_p":1,"enti_t":1,"perc":"23,88","vot_m":0,"vot_f":0,"vot_t":192,"perc_r":null},{"com":4,"dt_com":20250609150000,"enti_p":1,"enti_t":1,"perc":"32,96","vot_m":112,"vot_f":153,"vot_t":265,"perc_r":null}]},{"tipo":"SEZIONE","desc":"SEZIONE 42","cod":42,"osp":"N","ele_m":352,"ele_f":401,"ele_t":753,"com_vot":[{"com":1,"dt_com":20250608120000,"enti_p":1,"enti_t":1,"perc":"8,76","vot_m":0,"vot_f":0,"vot_t":66,"perc_r":null},{"com":2,"dt_com":20250608190000,"enti_p":1,"enti_t":1,"perc":"18,59","vot_m":0,"vot_f":0,"vot_t":140,"perc_r":null},{"com":3,"dt_com":20250608230000,"enti_p":1,"enti_t":1,"perc":"23,37","vot_m":0,"vot_f":0,"vot_t":176,"perc_r":null},{"com":4,"dt_com":20250609150000,"enti_p":1,"enti_t":1,"perc":"28,82","vot_m":103,"vot_f":114,"vot_t":217,"perc_r":null}]},{"tipo":"SEZIONE","desc":"SEZIONE 43","cod":43,"osp":"N","ele_m":260,"ele_f":441,"ele_t":701,"com_vot":[{"com":1,"dt_com":20250608120000,"enti_p":1,"enti_t":1,"perc":"6,99","vot_m":0,"vot_f":0,"vot_t":49,"perc_r":null},{"com":2,"dt_com":20250608190000,"enti_p":1,"enti_t":1,"perc":"14,69","vot_m":0,"vot_f":0,"vot_t":103,"perc_r":null},{"com":3,"dt_com":20250608230000,"enti_p":1,"enti_t":1,"perc":"19,69","vot_m":0,"vot_f":0,"vot_t":138,"perc_r":null},{"com":4,"dt_com":20250609150000,"enti_p":1,"enti_t":1,"perc":"25,11","vot_m":74,"vot_f":102,"vot_t":176,"perc_r":null}]},{"tipo":"SEZIONE","desc":"SEZIONE 44","cod":44,"osp":"N","ele_m":320,"ele_f":354,"ele_t":674,"com_vot":[{"com":1,"dt_com":20250608120000,"enti_p":1,"enti_t":1,"perc":"14,24","vot_m":0,"vot_f":0,"vot_t":96,"perc_r":null},{"com":2,"dt_com":20250608190000,"enti_p":1,"enti_t":1,"perc":"19,44","vot_m":0,"vot_f":0,"vot_t":131,"perc_r":null},{"com":3,"dt_com":20250608230000,"enti_p":1,"enti_t":1,"perc":"24,93","vot_m":0,"vot_f":0,"vot_t":168,"perc_r":null},{"com":4,"dt_com":20250609150000,"enti_p":1,"enti_t":1,"perc":"32,05","vot_m":105,"vot_f":111,"vot_t":216,"perc_r":null}]},{"tipo":"SEZIONE","desc":"SEZIONE 45","cod":45,"osp":"N","ele_m":433,"ele_f":447,"ele_t":880,"com_vot":[{"com":1,"dt_com":20250608120000,"enti_p":1,"enti_t":1,"perc":"6,70","vot_m":0,"vot_f":0,"vot_t":59,"perc_r":null},{"com":2,"dt_com":20250608190000,"enti_p":1,"enti_t":1,"perc":"20,11","vot_m":0,"vot_f":0,"vot_t":177,"perc_r":null},{"com":3,"dt_com":20250608230000,"enti_p":1,"enti_t":1,"perc":"29,32","vot_m":0,"vot_f":0,"vot_t":258,"perc_r":null},{"com":4,"dt_com":20250609150000,"enti_p":1,"enti_t":1,"perc":"35,23","vot_m":153,"vot_f":157,"vot_t":310,"perc_r":null}]},{"tipo":"SEZIONE","desc":"SEZIONE 46","cod":46,"osp":"N","ele_m":325,"ele_f":394,"ele_t":719,"com_vot":[{"com":1,"dt_com":20250608120000,"enti_p":1,"enti_t":1,"perc":"7,93","vot_m":0,"vot_f":0,"vot_t":57,"perc_r":null},{"com":2,"dt_com":20250608190000,"enti_p":1,"enti_t":1,"perc":"17,66","vot_m":0,"vot_f":0,"vot_t":127,"perc_r":null},{"com":3,"dt_com":20250608230000,"enti_p":1,"enti_t":1,"perc":"23,23","vot_m":0,"vot_f":0,"vot_t":167,"perc_r":null},{"com":4,"dt_com":20250609150000,"enti_p":1,"enti_t":1,"perc":"28,79","vot_m":100,"vot_f":107,"vot_t":207,"perc_r":null}]},{"tipo":"SEZIONE","desc":"SEZIONE 47","cod":47,"osp":"N","ele_m":345,"ele_f":387,"ele_t":732,"com_vot":[{"com":1,"dt_com":20250608120000,"enti_p":1,"enti_t":1,"perc":"7,65","vot_m":0,"vot_f":0,"vot_t":56,"perc_r":null},{"com":2,"dt_com":20250608190000,"enti_p":1,"enti_t":1,"perc":"17,76","vot_m":0,"vot_f":0,"vot_t":130,"perc_r":null},{"com":3,"dt_com":20250608230000,"enti_p":1,"enti_t":1,"perc":"25,82","vot_m":0,"vot_f":0,"vot_t":189,"perc_r":null},{"com":4,"dt_com":20250609150000,"enti_p":1,"enti_t":1,"perc":"32,24","vot_m":105,"vot_f":131,"vot_t":236,"perc_r":null}]},{"tipo":"SEZIONE","desc":"SEZIONE 48","cod":48,"osp":"N","ele_m":412,"ele_f":451,"ele_t":863,"com_vot":[{"com":1,"dt_com":20250608120000,"enti_p":1,"enti_t":1,"perc":"9,97","vot_m":0,"vot_f":0,"vot_t":86,"perc_r":null},{"com":2,"dt_com":20250608190000,"enti_p":1,"enti_t":1,"perc":"20,28","vot_m":0,"vot_f":0,"vot_t":175,"perc_r":null},{"com":3,"dt_com":20250608230000,"enti_p":1,"enti_t":1,"perc":"27,93","vot_m":0,"vot_f":0,"vot_t":241,"perc_r":null},{"com":4,"dt_com":20250609150000,"enti_p":1,"enti_t":1,"perc":"34,76","vot_m":140,"vot_f":160,"vot_t":300,"perc_r":null}]},{"tipo":"SEZIONE","desc":"SEZIONE 49","cod":49,"osp":"N","ele_m":377,"ele_f":392,"ele_t":769,"com_vot":[{"com":1,"dt_com":20250608120000,"enti_p":1,"enti_t":1,"perc":"9,23","vot_m":0,"vot_f":0,"vot_t":71,"perc_r":null},{"com":2,"dt_com":20250608190000,"enti_p":1,"enti_t":1,"perc":"19,77","vot_m":0,"vot_f":0,"vot_t":152,"perc_r":null},{"com":3,"dt_com":20250608230000,"enti_p":1,"enti_t":1,"perc":"25,36","vot_m":0,"vot_f":0,"vot_t":195,"perc_r":null},{"com":4,"dt_com":20250609150000,"enti_p":1,"enti_t":1,"perc":"34,85","vot_m":127,"vot_f":141,"vot_t":268,"perc_r":null}]},{"tipo":"SEZIONE","desc":"SEZIONE 50","cod":50,"osp":"N","ele_m":421,"ele_f":474,"ele_t":895,"com_vot":[{"com":1,"dt_com":20250608120000,"enti_p":1,"enti_t":1,"perc":"8,16","vot_m":0,"vot_f":0,"vot_t":73,"perc_r":null},{"com":2,"dt_com":20250608190000,"enti_p":1,"enti_t":1,"perc":"19,33","vot_m":0,"vot_f":0,"vot_t":173,"perc_r":null},{"com":3,"dt_com":20250608230000,"enti_p":1,"enti_t":1,"perc":"27,60","vot_m":0,"vot_f":0,"vot_t":247,"perc_r":null},{"com":4,"dt_com":20250609150000,"enti_p":1,"enti_t":1,"perc":"34,08","vot_m":144,"vot_f":161,"vot_t":305,"perc_r":null}]},{"tipo":"SEZIONE","desc":"SEZIONE 51","cod":51,"osp":"N","ele_m":329,"ele_f":354,"ele_t":683,"com_vot":[{"com":1,"dt_com":20250608120000,"enti_p":1,"enti_t":1,"perc":"8,05","vot_m":0,"vot_f":0,"vot_t":55,"perc_r":null},{"com":2,"dt_com":20250608190000,"enti_p":1,"enti_t":1,"perc":"19,18","vot_m":0,"vot_f":0,"vot_t":131,"perc_r":null},{"com":3,"dt_com":20250608230000,"enti_p":1,"enti_t":1,"perc":"26,65","vot_m":0,"vot_f":0,"vot_t":182,"perc_r":null},{"com":4,"dt_com":20250609150000,"enti_p":1,"enti_t":1,"perc":"31,63","vot_m":100,"vot_f":116,"vot_t":216,"perc_r":null}]},{"tipo":"SEZIONE","desc":"SEZIONE 52","cod":52,"osp":"N","ele_m":267,"ele_f":302,"ele_t":569,"com_vot":[{"com":1,"dt_com":20250608120000,"enti_p":1,"enti_t":1,"perc":"4,39","vot_m":0,"vot_f":0,"vot_t":25,"perc_r":null},{"com":2,"dt_com":20250608190000,"enti_p":1,"enti_t":1,"perc":"13,18","vot_m":0,"vot_f":0,"vot_t":75,"perc_r":null},{"com":3,"dt_com":20250608230000,"enti_p":1,"enti_t":1,"perc":"18,45","vot_m":0,"vot_f":0,"vot_t":105,"perc_r":null},{"com":4,"dt_com":20250609150000,"enti_p":1,"enti_t":1,"perc":"24,78","vot_m":65,"vot_f":76,"vot_t":141,"perc_r":null}]},{"tipo":"SEZIONE","desc":"SEZIONE 53","cod":53,"osp":"N","ele_m":380,"ele_f":379,"ele_t":759,"com_vot":[{"com":1,"dt_com":20250608120000,"enti_p":1,"enti_t":1,"perc":"8,30","vot_m":0,"vot_f":0,"vot_t":63,"perc_r":null},{"com":2,"dt_com":20250608190000,"enti_p":1,"enti_t":1,"perc":"16,34","vot_m":0,"vot_f":0,"vot_t":124,"perc_r":null},{"com":3,"dt_com":20250608230000,"enti_p":1,"enti_t":1,"perc":"21,74","vot_m":0,"vot_f":0,"vot_t":165,"perc_r":null},{"com":4,"dt_com":20250609150000,"enti_p":1,"enti_t":1,"perc":"27,01","vot_m":104,"vot_f":101,"vot_t":205,"perc_r":null}]},{"tipo":"SEZIONE","desc":"SEZIONE 54","cod":54,"osp":"N","ele_m":354,"ele_f":396,"ele_t":750,"com_vot":[{"com":1,"dt_com":20250608120000,"enti_p":1,"enti_t":1,"perc":"7,47","vot_m":0,"vot_f":0,"vot_t":56,"perc_r":null},{"com":2,"dt_com":20250608190000,"enti_p":1,"enti_t":1,"perc":"16,53","vot_m":0,"vot_f":0,"vot_t":124,"perc_r":null},{"com":3,"dt_com":20250608230000,"enti_p":1,"enti_t":1,"perc":"23,87","vot_m":0,"vot_f":0,"vot_t":179,"perc_r":null},{"com":4,"dt_com":20250609150000,"enti_p":1,"enti_t":1,"perc":"30,67","vot_m":110,"vot_f":120,"vot_t":230,"perc_r":null}]},{"tipo":"SEZIONE","desc":"SEZIONE 55","cod":55,"osp":"N","ele_m":233,"ele_f":234,"ele_t":467,"com_vot":[{"com":1,"dt_com":20250608120000,"enti_p":1,"enti_t":1,"perc":"5,57","vot_m":0,"vot_f":0,"vot_t":26,"perc_r":null},{"com":2,"dt_com":20250608190000,"enti_p":1,"enti_t":1,"perc":"10,49","vot_m":0,"vot_f":0,"vot_t":49,"perc_r":null},{"com":3,"dt_com":20250608230000,"enti_p":1,"enti_t":1,"perc":"15,20","vot_m":0,"vot_f":0,"vot_t":71,"perc_r":null},{"com":4,"dt_com":20250609150000,"enti_p":1,"enti_t":1,"perc":"20,56","vot_m":50,"vot_f":46,"vot_t":96,"perc_r":null}]},{"tipo":"SEZIONE","desc":"SEZIONE 56","cod":56,"osp":"N","ele_m":408,"ele_f":419,"ele_t":827,"com_vot":[{"com":1,"dt_com":20250608120000,"enti_p":1,"enti_t":1,"perc":"6,77","vot_m":0,"vot_f":0,"vot_t":56,"perc_r":null},{"com":2,"dt_com":20250608190000,"enti_p":1,"enti_t":1,"perc":"19,11","vot_m":0,"vot_f":0,"vot_t":158,"perc_r":null},{"com":3,"dt_com":20250608230000,"enti_p":1,"enti_t":1,"perc":"27,21","vot_m":0,"vot_f":0,"vot_t":225,"perc_r":null},{"com":4,"dt_com":20250609150000,"enti_p":1,"enti_t":1,"perc":"36,88","vot_m":137,"vot_f":168,"vot_t":305,"perc_r":null}]},{"tipo":"SEZIONE","desc":"SEZIONE 57","cod":57,"osp":"N","ele_m":347,"ele_f":370,"ele_t":717,"com_vot":[{"com":1,"dt_com":20250608120000,"enti_p":1,"enti_t":1,"perc":"5,86","vot_m":0,"vot_f":0,"vot_t":42,"perc_r":null},{"com":2,"dt_com":20250608190000,"enti_p":1,"enti_t":1,"perc":"13,95","vot_m":0,"vot_f":0,"vot_t":100,"perc_r":null},{"com":3,"dt_com":20250608230000,"enti_p":1,"enti_t":1,"perc":"20,50","vot_m":0,"vot_f":0,"vot_t":147,"perc_r":null},{"com":4,"dt_com":20250609150000,"enti_p":1,"enti_t":1,"perc":"27,89","vot_m":107,"vot_f":93,"vot_t":200,"perc_r":null}]},{"tipo":"SEZIONE","desc":"SEZIONE 58","cod":58,"osp":"N","ele_m":491,"ele_f":476,"ele_t":967,"com_vot":[{"com":1,"dt_com":20250608120000,"enti_p":1,"enti_t":1,"perc":"6,72","vot_m":0,"vot_f":0,"vot_t":65,"perc_r":null},{"com":2,"dt_com":20250608190000,"enti_p":1,"enti_t":1,"perc":"16,55","vot_m":0,"vot_f":0,"vot_t":160,"perc_r":null},{"com":3,"dt_com":20250608230000,"enti_p":1,"enti_t":1,"perc":"26,06","vot_m":0,"vot_f":0,"vot_t":252,"perc_r":null},{"com":4,"dt_com":20250609150000,"enti_p":1,"enti_t":1,"perc":"34,44","vot_m":153,"vot_f":180,"vot_t":333,"perc_r":null}]},{"tipo":"SEZIONE","desc":"SEZIONE 59","cod":59,"osp":"N","ele_m":369,"ele_f":377,"ele_t":746,"com_vot":[{"com":1,"dt_com":20250608120000,"enti_p":1,"enti_t":1,"perc":"4,69","vot_m":0,"vot_f":0,"vot_t":35,"perc_r":null},{"com":2,"dt_com":20250608190000,"enti_p":1,"enti_t":1,"perc":"16,35","vot_m":0,"vot_f":0,"vot_t":122,"perc_r":null},{"com":3,"dt_com":20250608230000,"enti_p":1,"enti_t":1,"perc":"21,05","vot_m":0,"vot_f":0,"vot_t":157,"perc_r":null},{"com":4,"dt_com":20250609150000,"enti_p":1,"enti_t":1,"perc":"28,28","vot_m":103,"vot_f":108,"vot_t":211,"perc_r":null}]},{"tipo":"SEZIONE","desc":"SEZIONE 60","cod":60,"osp":"N","ele_m":316,"ele_f":331,"ele_t":647,"com_vot":[{"com":1,"dt_com":20250608120000,"enti_p":1,"enti_t":1,"perc":"6,34","vot_m":0,"vot_f":0,"vot_t":41,"perc_r":null},{"com":2,"dt_com":20250608190000,"enti_p":1,"enti_t":1,"perc":"13,91","vot_m":0,"vot_f":0,"vot_t":90,"perc_r":null},{"com":3,"dt_com":20250608230000,"enti_p":1,"enti_t":1,"perc":"20,56","vot_m":0,"vot_f":0,"vot_t":133,"perc_r":null},{"com":4,"dt_com":20250609150000,"enti_p":1,"enti_t":1,"perc":"28,59","vot_m":89,"vot_f":96,"vot_t":185,"perc_r":null}]},{"tipo":"SEZIONE","desc":"SEZIONE 61","cod":61,"osp":"N","ele_m":300,"ele_f":308,"ele_t":608,"com_vot":[{"com":1,"dt_com":20250608120000,"enti_p":1,"enti_t":1,"perc":"4,28","vot_m":0,"vot_f":0,"vot_t":26,"perc_r":null},{"com":2,"dt_com":20250608190000,"enti_p":1,"enti_t":1,"perc":"12,34","vot_m":0,"vot_f":0,"vot_t":75,"perc_r":null},{"com":3,"dt_com":20250608230000,"enti_p":1,"enti_t":1,"perc":"21,55","vot_m":0,"vot_f":0,"vot_t":131,"perc_r":null},{"com":4,"dt_com":20250609150000,"enti_p":1,"enti_t":1,"perc":"29,44","vot_m":83,"vot_f":96,"vot_t":179,"perc_r":null}]},{"tipo":"SEZIONE","desc":"SEZIONE 62","cod":62,"osp":"N","ele_m":418,"ele_f":460,"ele_t":878,"com_vot":[{"com":1,"dt_com":20250608120000,"enti_p":1,"enti_t":1,"perc":"4,33","vot_m":0,"vot_f":0,"vot_t":38,"perc_r":null},{"com":2,"dt_com":20250608190000,"enti_p":1,"enti_t":1,"perc":"14,12","vot_m":0,"vot_f":0,"vot_t":124,"perc_r":null},{"com":3,"dt_com":20250608230000,"enti_p":1,"enti_t":1,"perc":"20,39","vot_m":0,"vot_f":0,"vot_t":179,"perc_r":null},{"com":4,"dt_com":20250609150000,"enti_p":1,"enti_t":1,"perc":"26,65","vot_m":115,"vot_f":119,"vot_t":234,"perc_r":null}]},{"tipo":"SEZIONE","desc":"SEZIONE 63","cod":63,"osp":"N","ele_m":446,"ele_f":446,"ele_t":892,"com_vot":[{"com":1,"dt_com":20250608120000,"enti_p":1,"enti_t":1,"perc":"6,28","vot_m":0,"vot_f":0,"vot_t":56,"perc_r":null},{"com":2,"dt_com":20250608190000,"enti_p":1,"enti_t":1,"perc":"14,01","vot_m":0,"vot_f":0,"vot_t":125,"perc_r":null},{"com":3,"dt_com":20250608230000,"enti_p":1,"enti_t":1,"perc":"20,74","vot_m":0,"vot_f":0,"vot_t":185,"perc_r":null},{"com":4,"dt_com":20250609150000,"enti_p":1,"enti_t":1,"perc":"28,48","vot_m":115,"vot_f":139,"vot_t":254,"perc_r":null}]},{"tipo":"SEZIONE","desc":"SEZIONE 64","cod":64,"osp":"N","ele_m":445,"ele_f":506,"ele_t":951,"com_vot":[{"com":1,"dt_com":20250608120000,"enti_p":1,"enti_t":1,"perc":"6,10","vot_m":0,"vot_f":0,"vot_t":58,"perc_r":null},{"com":2,"dt_com":20250608190000,"enti_p":1,"enti_t":1,"perc":"16,93","vot_m":0,"vot_f":0,"vot_t":161,"perc_r":null},{"com":3,"dt_com":20250608230000,"enti_p":1,"enti_t":1,"perc":"25,03","vot_m":0,"vot_f":0,"vot_t":238,"perc_r":null},{"com":4,"dt_com":20250609150000,"enti_p":1,"enti_t":1,"perc":"33,23","vot_m":147,"vot_f":169,"vot_t":316,"perc_r":null}]},{"tipo":"SEZIONE","desc":"SEZIONE 65","cod":65,"osp":"N","ele_m":375,"ele_f":377,"ele_t":752,"com_vot":[{"com":1,"dt_com":20250608120000,"enti_p":1,"enti_t":1,"perc":"7,18","vot_m":0,"vot_f":0,"vot_t":54,"perc_r":null},{"com":2,"dt_com":20250608190000,"enti_p":1,"enti_t":1,"perc":"17,29","vot_m":0,"vot_f":0,"vot_t":130,"perc_r":null},{"com":3,"dt_com":20250608230000,"enti_p":1,"enti_t":1,"perc":"22,47","vot_m":0,"vot_f":0,"vot_t":169,"perc_r":null},{"com":4,"dt_com":20250609150000,"enti_p":1,"enti_t":1,"perc":"28,46","vot_m":109,"vot_f":105,"vot_t":214,"perc_r":null}]},{"tipo":"SEZIONE","desc":"SEZIONE 66","cod":66,"osp":"N","ele_m":293,"ele_f":304,"ele_t":597,"com_vot":[{"com":1,"dt_com":20250608120000,"enti_p":1,"enti_t":1,"perc":"3,02","vot_m":0,"vot_f":0,"vot_t":18,"perc_r":null},{"com":2,"dt_com":20250608190000,"enti_p":1,"enti_t":1,"perc":"10,89","vot_m":0,"vot_f":0,"vot_t":65,"perc_r":null},{"com":3,"dt_com":20250608230000,"enti_p":1,"enti_t":1,"perc":"18,76","vot_m":0,"vot_f":0,"vot_t":112,"perc_r":null},{"com":4,"dt_com":20250609150000,"enti_p":1,"enti_t":1,"perc":"25,13","vot_m":68,"vot_f":82,"vot_t":150,"perc_r":null}]},{"tipo":"SEZIONE","desc":"SEZIONE 67","cod":67,"osp":"N","ele_m":281,"ele_f":315,"ele_t":596,"com_vot":[{"com":1,"dt_com":20250608120000,"enti_p":1,"enti_t":1,"perc":"6,71","vot_m":0,"vot_f":0,"vot_t":40,"perc_r":null},{"com":2,"dt_com":20250608190000,"enti_p":1,"enti_t":1,"perc":"12,92","vot_m":0,"vot_f":0,"vot_t":77,"perc_r":null},{"com":3,"dt_com":20250608230000,"enti_p":1,"enti_t":1,"perc":"16,95","vot_m":0,"vot_f":0,"vot_t":101,"perc_r":null},{"com":4,"dt_com":20250609150000,"enti_p":1,"enti_t":1,"perc":"22,65","vot_m":59,"vot_f":76,"vot_t":135,"perc_r":null}]},{"tipo":"SEZIONE","desc":"SEZIONE 68","cod":68,"osp":"N","ele_m":412,"ele_f":387,"ele_t":799,"com_vot":[{"com":1,"dt_com":20250608120000,"enti_p":1,"enti_t":1,"perc":"6,63","vot_m":0,"vot_f":0,"vot_t":53,"perc_r":null},{"com":2,"dt_com":20250608190000,"enti_p":1,"enti_t":1,"perc":"13,27","vot_m":0,"vot_f":0,"vot_t":106,"perc_r":null},{"com":3,"dt_com":20250608230000,"enti_p":1,"enti_t":1,"perc":"17,90","vot_m":0,"vot_f":0,"vot_t":143,"perc_r":null},{"com":4,"dt_com":20250609150000,"enti_p":1,"enti_t":1,"perc":"22,65","vot_m":90,"vot_f":91,"vot_t":181,"perc_r":null}]},{"tipo":"SEZIONE","desc":"SEZIONE 69","cod":69,"osp":"N","ele_m":357,"ele_f":363,"ele_t":720,"com_vot":[{"com":1,"dt_com":20250608120000,"enti_p":1,"enti_t":1,"perc":"7,64","vot_m":0,"vot_f":0,"vot_t":55,"perc_r":null},{"com":2,"dt_com":20250608190000,"enti_p":1,"enti_t":1,"perc":"15,69","vot_m":0,"vot_f":0,"vot_t":113,"perc_r":null},{"com":3,"dt_com":20250608230000,"enti_p":1,"enti_t":1,"perc":"20,83","vot_m":0,"vot_f":0,"vot_t":150,"perc_r":null},{"com":4,"dt_com":20250609150000,"enti_p":1,"enti_t":1,"perc":"27,08","vot_m":90,"vot_f":105,"vot_t":195,"perc_r":null}]},{"tipo":"SEZIONE","desc":"SEZIONE 70","cod":70,"osp":"N","ele_m":303,"ele_f":304,"ele_t":607,"com_vot":[{"com":1,"dt_com":20250608120000,"enti_p":1,"enti_t":1,"perc":"4,61","vot_m":0,"vot_f":0,"vot_t":28,"perc_r":null},{"com":2,"dt_com":20250608190000,"enti_p":1,"enti_t":1,"perc":"13,84","vot_m":0,"vot_f":0,"vot_t":84,"perc_r":null},{"com":3,"dt_com":20250608230000,"enti_p":1,"enti_t":1,"perc":"20,59","vot_m":0,"vot_f":0,"vot_t":125,"perc_r":null},{"com":4,"dt_com":20250609150000,"enti_p":1,"enti_t":1,"perc":"27,51","vot_m":89,"vot_f":78,"vot_t":167,"perc_r":null}]},{"tipo":"SEZIONE","desc":"SEZIONE 71","cod":71,"osp":"N","ele_m":315,"ele_f":308,"ele_t":623,"com_vot":[{"com":1,"dt_com":20250608120000,"enti_p":1,"enti_t":1,"perc":"6,74","vot_m":0,"vot_f":0,"vot_t":42,"perc_r":null},{"com":2,"dt_com":20250608190000,"enti_p":1,"enti_t":1,"perc":"13,48","vot_m":0,"vot_f":0,"vot_t":84,"perc_r":null},{"com":3,"dt_com":20250608230000,"enti_p":1,"enti_t":1,"perc":"19,10","vot_m":0,"vot_f":0,"vot_t":119,"perc_r":null},{"com":4,"dt_com":20250609150000,"enti_p":1,"enti_t":1,"perc":"24,24","vot_m":72,"vot_f":79,"vot_t":151,"perc_r":null}]},{"tipo":"SEZIONE","desc":"SEZIONE 72","cod":72,"osp":"N","ele_m":385,"ele_f":350,"ele_t":735,"com_vot":[{"com":1,"dt_com":20250608120000,"enti_p":1,"enti_t":1,"perc":"5,17","vot_m":0,"vot_f":0,"vot_t":38,"perc_r":null},{"com":2,"dt_com":20250608190000,"enti_p":1,"enti_t":1,"perc":"12,79","vot_m":0,"vot_f":0,"vot_t":94,"perc_r":null},{"com":3,"dt_com":20250608230000,"enti_p":1,"enti_t":1,"perc":"19,46","vot_m":0,"vot_f":0,"vot_t":143,"perc_r":null},{"com":4,"dt_com":20250609150000,"enti_p":1,"enti_t":1,"perc":"25,44","vot_m":88,"vot_f":99,"vot_t":187,"perc_r":null}]},{"tipo":"SEZIONE","desc":"SEZIONE 73","cod":73,"osp":"N","ele_m":358,"ele_f":325,"ele_t":683,"com_vot":[{"com":1,"dt_com":20250608120000,"enti_p":1,"enti_t":1,"perc":"9,52","vot_m":0,"vot_f":0,"vot_t":65,"perc_r":null},{"com":2,"dt_com":20250608190000,"enti_p":1,"enti_t":1,"perc":"20,64","vot_m":0,"vot_f":0,"vot_t":141,"perc_r":null},{"com":3,"dt_com":20250608230000,"enti_p":1,"enti_t":1,"perc":"26,06","vot_m":0,"vot_f":0,"vot_t":178,"perc_r":null},{"com":4,"dt_com":20250609150000,"enti_p":1,"enti_t":1,"perc":"33,24","vot_m":111,"vot_f":116,"vot_t":227,"perc_r":null}]},{"tipo":"SEZIONE","desc":"SEZIONE 74","cod":74,"osp":"N","ele_m":304,"ele_f":326,"ele_t":630,"com_vot":[{"com":1,"dt_com":20250608120000,"enti_p":1,"enti_t":1,"perc":"6,03","vot_m":0,"vot_f":0,"vot_t":38,"perc_r":null},{"com":2,"dt_com":20250608190000,"enti_p":1,"enti_t":1,"perc":"11,27","vot_m":0,"vot_f":0,"vot_t":71,"perc_r":null},{"com":3,"dt_com":20250608230000,"enti_p":1,"enti_t":1,"perc":"16,83","vot_m":0,"vot_f":0,"vot_t":106,"perc_r":null},{"com":4,"dt_com":20250609150000,"enti_p":1,"enti_t":1,"perc":"22,22","vot_m":67,"vot_f":73,"vot_t":140,"perc_r":null}]},{"tipo":"SEZIONE","desc":"SEZIONE 75","cod":75,"osp":"N","ele_m":422,"ele_f":449,"ele_t":871,"com_vot":[{"com":1,"dt_com":20250608120000,"enti_p":1,"enti_t":1,"perc":"5,40","vot_m":0,"vot_f":0,"vot_t":47,"perc_r":null},{"com":2,"dt_com":20250608190000,"enti_p":1,"enti_t":1,"perc":"16,19","vot_m":0,"vot_f":0,"vot_t":141,"perc_r":null},{"com":3,"dt_com":20250608230000,"enti_p":1,"enti_t":1,"perc":"23,19","vot_m":0,"vot_f":0,"vot_t":202,"perc_r":null},{"com":4,"dt_com":20250609150000,"enti_p":1,"enti_t":1,"perc":"29,16","vot_m":124,"vot_f":130,"vot_t":254,"perc_r":null}]},{"tipo":"SEZIONE","desc":"SEZIONE 76","cod":76,"osp":"N","ele_m":402,"ele_f":420,"ele_t":822,"com_vot":[{"com":1,"dt_com":20250608120000,"enti_p":1,"enti_t":1,"perc":"5,72","vot_m":0,"vot_f":0,"vot_t":47,"perc_r":null},{"com":2,"dt_com":20250608190000,"enti_p":1,"enti_t":1,"perc":"14,36","vot_m":0,"vot_f":0,"vot_t":118,"perc_r":null},{"com":3,"dt_com":20250608230000,"enti_p":1,"enti_t":1,"perc":"19,83","vot_m":0,"vot_f":0,"vot_t":163,"perc_r":null},{"com":4,"dt_com":20250609150000,"enti_p":1,"enti_t":1,"perc":"26,16","vot_m":109,"vot_f":106,"vot_t":215,"perc_r":null}]},{"tipo":"SEZIONE","desc":"SEZIONE 77","cod":77,"osp":"N","ele_m":334,"ele_f":326,"ele_t":660,"com_vot":[{"com":1,"dt_com":20250608120000,"enti_p":1,"enti_t":1,"perc":"5,76","vot_m":0,"vot_f":0,"vot_t":38,"perc_r":null},{"com":2,"dt_com":20250608190000,"enti_p":1,"enti_t":1,"perc":"12,58","vot_m":0,"vot_f":0,"vot_t":83,"perc_r":null},{"com":3,"dt_com":20250608230000,"enti_p":1,"enti_t":1,"perc":"20,45","vot_m":0,"vot_f":0,"vot_t":135,"perc_r":null},{"com":4,"dt_com":20250609150000,"enti_p":1,"enti_t":1,"perc":"26,82","vot_m":89,"vot_f":88,"vot_t":177,"perc_r":null}]},{"tipo":"SEZIONE","desc":"SEZIONE 78","cod":78,"osp":"N","ele_m":385,"ele_f":446,"ele_t":831,"com_vot":[{"com":1,"dt_com":20250608120000,"enti_p":1,"enti_t":1,"perc":"6,98","vot_m":0,"vot_f":0,"vot_t":58,"perc_r":null},{"com":2,"dt_com":20250608190000,"enti_p":1,"enti_t":1,"perc":"16,73","vot_m":0,"vot_f":0,"vot_t":139,"perc_r":null},{"com":3,"dt_com":20250608230000,"enti_p":1,"enti_t":1,"perc":"19,86","vot_m":0,"vot_f":0,"vot_t":165,"perc_r":null},{"com":4,"dt_com":20250609150000,"enti_p":1,"enti_t":1,"perc":"24,91","vot_m":96,"vot_f":111,"vot_t":207,"perc_r":null}]},{"tipo":"SEZIONE","desc":"SEZIONE 79","cod":79,"osp":"N","ele_m":394,"ele_f":393,"ele_t":787,"com_vot":[{"com":1,"dt_com":20250608120000,"enti_p":1,"enti_t":1,"perc":"5,46","vot_m":0,"vot_f":0,"vot_t":43,"perc_r":null},{"com":2,"dt_com":20250608190000,"enti_p":1,"enti_t":1,"perc":"16,39","vot_m":0,"vot_f":0,"vot_t":129,"perc_r":null},{"com":3,"dt_com":20250608230000,"enti_p":1,"enti_t":1,"perc":"23,76","vot_m":0,"vot_f":0,"vot_t":187,"perc_r":null},{"com":4,"dt_com":20250609150000,"enti_p":1,"enti_t":1,"perc":"29,73","vot_m":119,"vot_f":115,"vot_t":234,"perc_r":null}]},{"tipo":"SEZIONE","desc":"SEZIONE 80","cod":80,"osp":"N","ele_m":345,"ele_f":382,"ele_t":727,"com_vot":[{"com":1,"dt_com":20250608120000,"enti_p":1,"enti_t":1,"perc":"5,09","vot_m":0,"vot_f":0,"vot_t":37,"perc_r":null},{"com":2,"dt_com":20250608190000,"enti_p":1,"enti_t":1,"perc":"11,55","vot_m":0,"vot_f":0,"vot_t":84,"perc_r":null},{"com":3,"dt_com":20250608230000,"enti_p":1,"enti_t":1,"perc":"20,08","vot_m":0,"vot_f":0,"vot_t":146,"perc_r":null},{"com":4,"dt_com":20250609150000,"enti_p":1,"enti_t":1,"perc":"27,10","vot_m":93,"vot_f":104,"vot_t":197,"perc_r":null}]},{"tipo":"SEZIONE","desc":"SEZIONE 81","cod":81,"osp":"N","ele_m":451,"ele_f":464,"ele_t":915,"com_vot":[{"com":1,"dt_com":20250608120000,"enti_p":1,"enti_t":1,"perc":"6,34","vot_m":0,"vot_f":0,"vot_t":58,"perc_r":null},{"com":2,"dt_com":20250608190000,"enti_p":1,"enti_t":1,"perc":"15,19","vot_m":0,"vot_f":0,"vot_t":139,"perc_r":null},{"com":3,"dt_com":20250608230000,"enti_p":1,"enti_t":1,"perc":"21,09","vot_m":0,"vot_f":0,"vot_t":193,"perc_r":null},{"com":4,"dt_com":20250609150000,"enti_p":1,"enti_t":1,"perc":"28,74","vot_m":120,"vot_f":143,"vot_t":263,"perc_r":null}]},{"tipo":"SEZIONE","desc":"SEZIONE 82","cod":82,"osp":"N","ele_m":458,"ele_f":520,"ele_t":978,"com_vot":[{"com":1,"dt_com":20250608120000,"enti_p":1,"enti_t":1,"perc":"7,46","vot_m":0,"vot_f":0,"vot_t":73,"perc_r":null},{"com":2,"dt_com":20250608190000,"enti_p":1,"enti_t":1,"perc":"18,20","vot_m":0,"vot_f":0,"vot_t":178,"perc_r":null},{"com":3,"dt_com":20250608230000,"enti_p":1,"enti_t":1,"perc":"23,01","vot_m":0,"vot_f":0,"vot_t":225,"perc_r":null},{"com":4,"dt_com":20250609150000,"enti_p":1,"enti_t":1,"perc":"30,78","vot_m":136,"vot_f":165,"vot_t":301,"perc_r":null}]},{"tipo":"SEZIONE","desc":"SEZIONE 83","cod":83,"osp":"N","ele_m":308,"ele_f":381,"ele_t":689,"com_vot":[{"com":1,"dt_com":20250608120000,"enti_p":1,"enti_t":1,"perc":"9,00","vot_m":0,"vot_f":0,"vot_t":62,"perc_r":null},{"com":2,"dt_com":20250608190000,"enti_p":1,"enti_t":1,"perc":"12,19","vot_m":0,"vot_f":0,"vot_t":84,"perc_r":null},{"com":3,"dt_com":20250608230000,"enti_p":1,"enti_t":1,"perc":"24,38","vot_m":0,"vot_f":0,"vot_t":168,"perc_r":null},{"com":4,"dt_com":20250609150000,"enti_p":1,"enti_t":1,"perc":"31,35","vot_m":111,"vot_f":105,"vot_t":216,"perc_r":null}]},{"tipo":"SEZIONE","desc":"SEZIONE 84","cod":84,"osp":"N","ele_m":186,"ele_f":185,"ele_t":371,"com_vot":[{"com":1,"dt_com":20250608120000,"enti_p":1,"enti_t":1,"perc":"5,66","vot_m":0,"vot_f":0,"vot_t":21,"perc_r":null},{"com":2,"dt_com":20250608190000,"enti_p":1,"enti_t":1,"perc":"18,06","vot_m":0,"vot_f":0,"vot_t":67,"perc_r":null},{"com":3,"dt_com":20250608230000,"enti_p":1,"enti_t":1,"perc":"24,53","vot_m":0,"vot_f":0,"vot_t":91,"perc_r":null},{"com":4,"dt_com":20250609150000,"enti_p":1,"enti_t":1,"perc":"33,15","vot_m":60,"vot_f":63,"vot_t":123,"perc_r":null}]},{"tipo":"SEZIONE","desc":"SEZIONE 85","cod":85,"osp":"N","ele_m":307,"ele_f":377,"ele_t":684,"com_vot":[{"com":1,"dt_com":20250608120000,"enti_p":1,"enti_t":1,"perc":"8,92","vot_m":0,"vot_f":0,"vot_t":61,"perc_r":null},{"com":2,"dt_com":20250608190000,"enti_p":1,"enti_t":1,"perc":"14,91","vot_m":0,"vot_f":0,"vot_t":102,"perc_r":null},{"com":3,"dt_com":20250608230000,"enti_p":1,"enti_t":1,"perc":"21,05","vot_m":0,"vot_f":0,"vot_t":144,"perc_r":null},{"com":4,"dt_com":20250609150000,"enti_p":1,"enti_t":1,"perc":"29,68","vot_m":88,"vot_f":115,"vot_t":203,"perc_r":null}]},{"tipo":"SEZIONE","desc":"SEZIONE 86","cod":86,"osp":"N","ele_m":324,"ele_f":403,"ele_t":727,"com_vot":[{"com":1,"dt_com":20250608120000,"enti_p":1,"enti_t":1,"perc":"9,49","vot_m":0,"vot_f":0,"vot_t":69,"perc_r":null},{"com":2,"dt_com":20250608190000,"enti_p":1,"enti_t":1,"perc":"20,36","vot_m":0,"vot_f":0,"vot_t":148,"perc_r":null},{"com":3,"dt_com":20250608230000,"enti_p":1,"enti_t":1,"perc":"26,00","vot_m":0,"vot_f":0,"vot_t":189,"perc_r":null},{"com":4,"dt_com":20250609150000,"enti_p":1,"enti_t":1,"perc":"32,60","vot_m":108,"vot_f":129,"vot_t":237,"perc_r":null}]},{"tipo":"SEZIONE","desc":"SEZIONE 87","cod":87,"osp":"N","ele_m":375,"ele_f":431,"ele_t":806,"com_vot":[{"com":1,"dt_com":20250608120000,"enti_p":1,"enti_t":1,"perc":"6,70","vot_m":0,"vot_f":0,"vot_t":54,"perc_r":null},{"com":2,"dt_com":20250608190000,"enti_p":1,"enti_t":1,"perc":"13,77","vot_m":0,"vot_f":0,"vot_t":111,"perc_r":null},{"com":3,"dt_com":20250608230000,"enti_p":1,"enti_t":1,"perc":"20,35","vot_m":0,"vot_f":0,"vot_t":164,"perc_r":null},{"com":4,"dt_com":20250609150000,"enti_p":1,"enti_t":1,"perc":"26,18","vot_m":104,"vot_f":107,"vot_t":211,"perc_r":null}]},{"tipo":"SEZIONE","desc":"SEZIONE 88","cod":88,"osp":"N","ele_m":400,"ele_f":384,"ele_t":784,"com_vot":[{"com":1,"dt_com":20250608120000,"enti_p":1,"enti_t":1,"perc":"9,18","vot_m":0,"vot_f":0,"vot_t":72,"perc_r":null},{"com":2,"dt_com":20250608190000,"enti_p":1,"enti_t":1,"perc":"17,22","vot_m":0,"vot_f":0,"vot_t":135,"perc_r":null},{"com":3,"dt_com":20250608230000,"enti_p":1,"enti_t":1,"perc":"21,17","vot_m":0,"vot_f":0,"vot_t":166,"perc_r":null},{"com":4,"dt_com":20250609150000,"enti_p":1,"enti_t":1,"perc":"25,89","vot_m":101,"vot_f":102,"vot_t":203,"perc_r":null}]},{"tipo":"SEZIONE","desc":"SEZIONE 89","cod":89,"osp":"N","ele_m":309,"ele_f":344,"ele_t":653,"com_vot":[{"com":1,"dt_com":20250608120000,"enti_p":1,"enti_t":1,"perc":"6,89","vot_m":0,"vot_f":0,"vot_t":45,"perc_r":null},{"com":2,"dt_com":20250608190000,"enti_p":1,"enti_t":1,"perc":"15,62","vot_m":0,"vot_f":0,"vot_t":102,"perc_r":null},{"com":3,"dt_com":20250608230000,"enti_p":1,"enti_t":1,"perc":"21,44","vot_m":0,"vot_f":0,"vot_t":140,"perc_r":null},{"com":4,"dt_com":20250609150000,"enti_p":1,"enti_t":1,"perc":"27,87","vot_m":84,"vot_f":98,"vot_t":182,"perc_r":null}]},{"tipo":"SEZIONE","desc":"SEZIONE 90","cod":90,"osp":"N","ele_m":355,"ele_f":443,"ele_t":798,"com_vot":[{"com":1,"dt_com":20250608120000,"enti_p":1,"enti_t":1,"perc":"8,02","vot_m":0,"vot_f":0,"vot_t":64,"perc_r":null},{"com":2,"dt_com":20250608190000,"enti_p":1,"enti_t":1,"perc":"17,17","vot_m":0,"vot_f":0,"vot_t":137,"perc_r":null},{"com":3,"dt_com":20250608230000,"enti_p":1,"enti_t":1,"perc":"26,07","vot_m":0,"vot_f":0,"vot_t":208,"perc_r":null},{"com":4,"dt_com":20250609150000,"enti_p":1,"enti_t":1,"perc":"31,83","vot_m":114,"vot_f":140,"vot_t":254,"perc_r":null}]},{"tipo":"SEZIONE","desc":"SEZIONE 91","cod":91,"osp":"N","ele_m":453,"ele_f":485,"ele_t":938,"com_vot":[{"com":1,"dt_com":20250608120000,"enti_p":1,"enti_t":1,"perc":"6,18","vot_m":0,"vot_f":0,"vot_t":58,"perc_r":null},{"com":2,"dt_com":20250608190000,"enti_p":1,"enti_t":1,"perc":"14,61","vot_m":0,"vot_f":0,"vot_t":137,"perc_r":null},{"com":3,"dt_com":20250608230000,"enti_p":1,"enti_t":1,"perc":"23,03","vot_m":0,"vot_f":0,"vot_t":216,"perc_r":null},{"com":4,"dt_com":20250609150000,"enti_p":1,"enti_t":1,"perc":"29,53","vot_m":131,"vot_f":146,"vot_t":277,"perc_r":null}]},{"tipo":"SEZIONE","desc":"SEZIONE 92","cod":92,"osp":"N","ele_m":405,"ele_f":431,"ele_t":836,"com_vot":[{"com":1,"dt_com":20250608120000,"enti_p":1,"enti_t":1,"perc":"7,42","vot_m":0,"vot_f":0,"vot_t":62,"perc_r":null},{"com":2,"dt_com":20250608190000,"enti_p":1,"enti_t":1,"perc":"15,91","vot_m":0,"vot_f":0,"vot_t":133,"perc_r":null},{"com":3,"dt_com":20250608230000,"enti_p":1,"enti_t":1,"perc":"22,37","vot_m":0,"vot_f":0,"vot_t":187,"perc_r":null},{"com":4,"dt_com":20250609150000,"enti_p":1,"enti_t":1,"perc":"28,71","vot_m":118,"vot_f":122,"vot_t":240,"perc_r":null}]},{"tipo":"SEZIONE","desc":"SEZIONE 93","cod":93,"osp":"N","ele_m":471,"ele_f":558,"ele_t":1029,"com_vot":[{"com":1,"dt_com":20250608120000,"enti_p":1,"enti_t":1,"perc":"8,45","vot_m":0,"vot_f":0,"vot_t":87,"perc_r":null},{"com":2,"dt_com":20250608190000,"enti_p":1,"enti_t":1,"perc":"17,20","vot_m":0,"vot_f":0,"vot_t":177,"perc_r":null},{"com":3,"dt_com":20250608230000,"enti_p":1,"enti_t":1,"perc":"25,46","vot_m":0,"vot_f":0,"vot_t":262,"perc_r":null},{"com":4,"dt_com":20250609150000,"enti_p":1,"enti_t":1,"perc":"32,26","vot_m":154,"vot_f":178,"vot_t":332,"perc_r":null}]}]}}
