{"int":{"st":"ESERCIZIO","c_ele":9,"t_ele":"Referendum","f_elet":"VOTANTI","dt_ele":20250608000000,"l_terr":"COMUNE","area":"I","dt_agg":20250609181806},"note":null,"scheda":[{"cod":5,"desc":null}],"enti":{"ente_p":{"desc":"ESTE","cod":370,"ele_m":6145,"ele_f":6686,"ele_t":12831,"com":[{"cod_reg":5,"com_att":4,"num_com":4}],"com_vot":[{"com":1,"dt_com":20250608120000,"enti_p":18,"enti_t":18,"perc":"7,97","vot_m":0,"vot_f":0,"vot_t":1023,"perc_r":null},{"com":2,"dt_com":20250608190000,"enti_p":18,"enti_t":18,"perc":"15,33","vot_m":0,"vot_f":0,"vot_t":1967,"perc_r":null},{"com":3,"dt_com":20250608230000,"enti_p":18,"enti_t":18,"perc":"20,57","vot_m":0,"vot_f":0,"vot_t":2639,"perc_r":null},{"com":4,"dt_com":20250609150000,"enti_p":18,"enti_t":18,"perc":"27,15","vot_m":1665,"vot_f":1819,"vot_t":3484,"perc_r":null}]},"enti_f":[{"tipo":"SEZIONE","desc":"SEZIONE 1","cod":1,"osp":"N","ele_m":412,"ele_f":453,"ele_t":865,"com_vot":[{"com":1,"dt_com":20250608120000,"enti_p":1,"enti_t":1,"perc":"9,94","vot_m":0,"vot_f":0,"vot_t":86,"perc_r":null},{"com":2,"dt_com":20250608190000,"enti_p":1,"enti_t":1,"perc":"16,99","vot_m":0,"vot_f":0,"vot_t":147,"perc_r":null},{"com":3,"dt_com":20250608230000,"enti_p":1,"enti_t":1,"perc":"24,39","vot_m":0,"vot_f":0,"vot_t":211,"perc_r":null},{"com":4,"dt_com":20250609150000,"enti_p":1,"enti_t":1,"perc":"30,52","vot_m":128,"vot_f":136,"vot_t":264,"perc_r":null}]},{"tipo":"SEZIONE","desc":"SEZIONE 2","cod":2,"osp":"N","ele_m":409,"ele_f":445,"ele_t":854,"com_vot":[{"com":1,"dt_com":20250608120000,"enti_p":1,"enti_t":1,"perc":"9,72","vot_m":0,"vot_f":0,"vot_t":83,"perc_r":null},{"com":2,"dt_com":20250608190000,"enti_p":1,"enti_t":1,"perc":"17,45","vot_m":0,"vot_f":0,"vot_t":149,"perc_r":null},{"com":3,"dt_com":20250608230000,"enti_p":1,"enti_t":1,"perc":"22,48","vot_m":0,"vot_f":0,"vot_t":192,"perc_r":null},{"com":4,"dt_com":20250609150000,"enti_p":1,"enti_t":1,"perc":"29,51","vot_m":115,"vot_f":137,"vot_t":252,"perc_r":null}]},{"tipo":"SEZIONE","desc":"SEZIONE 3","cod":3,"osp":"N","ele_m":336,"ele_f":389,"ele_t":725,"com_vot":[{"com":1,"dt_com":20250608120000,"enti_p":1,"enti_t":1,"perc":"9,24","vot_m":0,"vot_f":0,"vot_t":67,"perc_r":null},{"com":2,"dt_com":20250608190000,"enti_p":1,"enti_t":1,"perc":"17,24","vot_m":0,"vot_f":0,"vot_t":125,"perc_r":null},{"com":3,"dt_com":20250608230000,"enti_p":1,"enti_t":1,"perc":"21,79","vot_m":0,"vot_f":0,"vot_t":158,"perc_r":null},{"com":4,"dt_com":20250609150000,"enti_p":1,"enti_t":1,"perc":"29,10","vot_m":102,"vot_f":109,"vot_t":211,"perc_r":null}]},{"tipo":"SEZIONE","desc":"SEZIONE 4","cod":4,"osp":"N","ele_m":312,"ele_f":326,"ele_t":638,"com_vot":[{"com":1,"dt_com":20250608120000,"enti_p":1,"enti_t":1,"perc":"7,52","vot_m":0,"vot_f":0,"vot_t":48,"perc_r":null},{"com":2,"dt_com":20250608190000,"enti_p":1,"enti_t":1,"perc":"13,17","vot_m":0,"vot_f":0,"vot_t":84,"perc_r":null},{"com":3,"dt_com":20250608230000,"enti_p":1,"enti_t":1,"perc":"20,53","vot_m":0,"vot_f":0,"vot_t":131,"perc_r":null},{"com":4,"dt_com":20250609150000,"enti_p":1,"enti_t":1,"perc":"27,90","vot_m":87,"vot_f":91,"vot_t":178,"perc_r":null}]},{"tipo":"SEZIONE","desc":"SEZIONE 5","cod":5,"osp":"N","ele_m":318,"ele_f":382,"ele_t":700,"com_vot":[{"com":1,"dt_com":20250608120000,"enti_p":1,"enti_t":1,"perc":"9,86","vot_m":0,"vot_f":0,"vot_t":69,"perc_r":null},{"com":2,"dt_com":20250608190000,"enti_p":1,"enti_t":1,"perc":"17,71","vot_m":0,"vot_f":0,"vot_t":124,"perc_r":null},{"com":3,"dt_com":20250608230000,"enti_p":1,"enti_t":1,"perc":"22,00","vot_m":0,"vot_f":0,"vot_t":154,"perc_r":null},{"com":4,"dt_com":20250609150000,"enti_p":1,"enti_t":1,"perc":"28,57","vot_m":82,"vot_f":118,"vot_t":200,"perc_r":null}]},{"tipo":"SEZIONE","desc":"SEZIONE 6","cod":6,"osp":"N","ele_m":410,"ele_f":438,"ele_t":848,"com_vot":[{"com":1,"dt_com":20250608120000,"enti_p":1,"enti_t":1,"perc":"8,73","vot_m":0,"vot_f":0,"vot_t":74,"perc_r":null},{"com":2,"dt_com":20250608190000,"enti_p":1,"enti_t":1,"perc":"16,39","vot_m":0,"vot_f":0,"vot_t":139,"perc_r":null},{"com":3,"dt_com":20250608230000,"enti_p":1,"enti_t":1,"perc":"20,75","vot_m":0,"vot_f":0,"vot_t":176,"perc_r":null},{"com":4,"dt_com":20250609150000,"enti_p":1,"enti_t":1,"perc":"25,59","vot_m":109,"vot_f":108,"vot_t":217,"perc_r":null}]},{"tipo":"SEZIONE","desc":"SEZIONE 7","cod":7,"osp":"N","ele_m":373,"ele_f":449,"ele_t":822,"com_vot":[{"com":1,"dt_com":20250608120000,"enti_p":1,"enti_t":1,"perc":"7,30","vot_m":0,"vot_f":0,"vot_t":60,"perc_r":null},{"com":2,"dt_com":20250608190000,"enti_p":1,"enti_t":1,"perc":"14,11","vot_m":0,"vot_f":0,"vot_t":116,"perc_r":null},{"com":3,"dt_com":20250608230000,"enti_p":1,"enti_t":1,"perc":"18,00","vot_m":0,"vot_f":0,"vot_t":148,"perc_r":null},{"com":4,"dt_com":20250609150000,"enti_p":1,"enti_t":1,"perc":"24,94","vot_m":91,"vot_f":114,"vot_t":205,"perc_r":null}]},{"tipo":"SEZIONE","desc":"SEZIONE 8","cod":8,"osp":"N","ele_m":350,"ele_f":443,"ele_t":793,"com_vot":[{"com":1,"dt_com":20250608120000,"enti_p":1,"enti_t":1,"perc":"3,78","vot_m":0,"vot_f":0,"vot_t":30,"perc_r":null},{"com":2,"dt_com":20250608190000,"enti_p":1,"enti_t":1,"perc":"9,08","vot_m":0,"vot_f":0,"vot_t":72,"perc_r":null},{"com":3,"dt_com":20250608230000,"enti_p":1,"enti_t":1,"perc":"13,24","vot_m":0,"vot_f":0,"vot_t":105,"perc_r":null},{"com":4,"dt_com":20250609150000,"enti_p":1,"enti_t":1,"perc":"19,29","vot_m":77,"vot_f":76,"vot_t":153,"perc_r":null}]},{"tipo":"SEZIONE","desc":"SEZIONE 9","cod":9,"osp":"N","ele_m":316,"ele_f":343,"ele_t":659,"com_vot":[{"com":1,"dt_com":20250608120000,"enti_p":1,"enti_t":1,"perc":"6,83","vot_m":0,"vot_f":0,"vot_t":45,"perc_r":null},{"com":2,"dt_com":20250608190000,"enti_p":1,"enti_t":1,"perc":"14,87","vot_m":0,"vot_f":0,"vot_t":98,"perc_r":null},{"com":3,"dt_com":20250608230000,"enti_p":1,"enti_t":1,"perc":"18,51","vot_m":0,"vot_f":0,"vot_t":122,"perc_r":null},{"com":4,"dt_com":20250609150000,"enti_p":1,"enti_t":1,"perc":"21,85","vot_m":70,"vot_f":74,"vot_t":144,"perc_r":null}]},{"tipo":"SEZIONE","desc":"SEZIONE 10","cod":10,"osp":"N","ele_m":374,"ele_f":397,"ele_t":771,"com_vot":[{"com":1,"dt_com":20250608120000,"enti_p":1,"enti_t":1,"perc":"6,49","vot_m":0,"vot_f":0,"vot_t":50,"perc_r":null},{"com":2,"dt_com":20250608190000,"enti_p":1,"enti_t":1,"perc":"14,79","vot_m":0,"vot_f":0,"vot_t":114,"perc_r":null},{"com":3,"dt_com":20250608230000,"enti_p":1,"enti_t":1,"perc":"19,84","vot_m":0,"vot_f":0,"vot_t":153,"perc_r":null},{"com":4,"dt_com":20250609150000,"enti_p":1,"enti_t":1,"perc":"26,20","vot_m":101,"vot_f":101,"vot_t":202,"perc_r":null}]},{"tipo":"SEZIONE","desc":"SEZIONE 11","cod":11,"osp":"N","ele_m":312,"ele_f":340,"ele_t":652,"com_vot":[{"com":1,"dt_com":20250608120000,"enti_p":1,"enti_t":1,"perc":"10,58","vot_m":0,"vot_f":0,"vot_t":69,"perc_r":null},{"com":2,"dt_com":20250608190000,"enti_p":1,"enti_t":1,"perc":"16,56","vot_m":0,"vot_f":0,"vot_t":108,"perc_r":null},{"com":3,"dt_com":20250608230000,"enti_p":1,"enti_t":1,"perc":"23,47","vot_m":0,"vot_f":0,"vot_t":153,"perc_r":null},{"com":4,"dt_com":20250609150000,"enti_p":1,"enti_t":1,"perc":"35,12","vot_m":118,"vot_f":111,"vot_t":229,"perc_r":null}]},{"tipo":"SEZIONE","desc":"SEZIONE 12","cod":12,"osp":"N","ele_m":360,"ele_f":389,"ele_t":749,"com_vot":[{"com":1,"dt_com":20250608120000,"enti_p":1,"enti_t":1,"perc":"8,54","vot_m":0,"vot_f":0,"vot_t":64,"perc_r":null},{"com":2,"dt_com":20250608190000,"enti_p":1,"enti_t":1,"perc":"17,76","vot_m":0,"vot_f":0,"vot_t":133,"perc_r":null},{"com":3,"dt_com":20250608230000,"enti_p":1,"enti_t":1,"perc":"25,37","vot_m":0,"vot_f":0,"vot_t":190,"perc_r":null},{"com":4,"dt_com":20250609150000,"enti_p":1,"enti_t":1,"perc":"32,98","vot_m":111,"vot_f":136,"vot_t":247,"perc_r":null}]},{"tipo":"SEZIONE","desc":"SEZIONE 13","cod":13,"osp":"N","ele_m":322,"ele_f":354,"ele_t":676,"com_vot":[{"com":1,"dt_com":20250608120000,"enti_p":1,"enti_t":1,"perc":"9,62","vot_m":0,"vot_f":0,"vot_t":65,"perc_r":null},{"com":2,"dt_com":20250608190000,"enti_p":1,"enti_t":1,"perc":"19,67","vot_m":0,"vot_f":0,"vot_t":133,"perc_r":null},{"com":3,"dt_com":20250608230000,"enti_p":1,"enti_t":1,"perc":"25,59","vot_m":0,"vot_f":0,"vot_t":173,"perc_r":null},{"com":4,"dt_com":20250609150000,"enti_p":1,"enti_t":1,"perc":"32,25","vot_m":100,"vot_f":118,"vot_t":218,"perc_r":null}]},{"tipo":"SEZIONE","desc":"SEZIONE 14","cod":14,"osp":"N","ele_m":347,"ele_f":369,"ele_t":716,"com_vot":[{"com":1,"dt_com":20250608120000,"enti_p":1,"enti_t":1,"perc":"10,20","vot_m":0,"vot_f":0,"vot_t":73,"perc_r":null},{"com":2,"dt_com":20250608190000,"enti_p":1,"enti_t":1,"perc":"19,69","vot_m":0,"vot_f":0,"vot_t":141,"perc_r":null},{"com":3,"dt_com":20250608230000,"enti_p":1,"enti_t":1,"perc":"27,09","vot_m":0,"vot_f":0,"vot_t":194,"perc_r":null},{"com":4,"dt_com":20250609150000,"enti_p":1,"enti_t":1,"perc":"33,38","vot_m":119,"vot_f":120,"vot_t":239,"perc_r":null}]},{"tipo":"SEZIONE","desc":"SEZIONE 15","cod":15,"osp":"N","ele_m":338,"ele_f":331,"ele_t":669,"com_vot":[{"com":1,"dt_com":20250608120000,"enti_p":1,"enti_t":1,"perc":"7,77","vot_m":0,"vot_f":0,"vot_t":52,"perc_r":null},{"com":2,"dt_com":20250608190000,"enti_p":1,"enti_t":1,"perc":"13,30","vot_m":0,"vot_f":0,"vot_t":89,"perc_r":null},{"com":3,"dt_com":20250608230000,"enti_p":1,"enti_t":1,"perc":"16,44","vot_m":0,"vot_f":0,"vot_t":110,"perc_r":null},{"com":4,"dt_com":20250609150000,"enti_p":1,"enti_t":1,"perc":"21,67","vot_m":67,"vot_f":78,"vot_t":145,"perc_r":null}]},{"tipo":"SEZIONE","desc":"SEZIONE 16","cod":16,"osp":"N","ele_m":257,"ele_f":235,"ele_t":492,"com_vot":[{"com":1,"dt_com":20250608120000,"enti_p":1,"enti_t":1,"perc":"4,27","vot_m":0,"vot_f":0,"vot_t":21,"perc_r":null},{"com":2,"dt_com":20250608190000,"enti_p":1,"enti_t":1,"perc":"9,96","vot_m":0,"vot_f":0,"vot_t":49,"perc_r":null},{"com":3,"dt_com":20250608230000,"enti_p":1,"enti_t":1,"perc":"14,63","vot_m":0,"vot_f":0,"vot_t":72,"perc_r":null},{"com":4,"dt_com":20250609150000,"enti_p":1,"enti_t":1,"perc":"18,50","vot_m":43,"vot_f":48,"vot_t":91,"perc_r":null}]},{"tipo":"SEZIONE","desc":"SEZIONE 17","cod":17,"osp":"N","ele_m":379,"ele_f":379,"ele_t":758,"com_vot":[{"com":1,"dt_com":20250608120000,"enti_p":1,"enti_t":1,"perc":"5,28","vot_m":0,"vot_f":0,"vot_t":40,"perc_r":null},{"com":2,"dt_com":20250608190000,"enti_p":1,"enti_t":1,"perc":"11,48","vot_m":0,"vot_f":0,"vot_t":87,"perc_r":null},{"com":3,"dt_com":20250608230000,"enti_p":1,"enti_t":1,"perc":"15,04","vot_m":0,"vot_f":0,"vot_t":114,"perc_r":null},{"com":4,"dt_com":20250609150000,"enti_p":1,"enti_t":1,"perc":"22,30","vot_m":89,"vot_f":80,"vot_t":169,"perc_r":null}]},{"tipo":"SEZIONE","desc":"SEZIONE 18","cod":18,"osp":"N","ele_m":220,"ele_f":224,"ele_t":444,"com_vot":[{"com":1,"dt_com":20250608120000,"enti_p":1,"enti_t":1,"perc":"6,08","vot_m":0,"vot_f":0,"vot_t":27,"perc_r":null},{"com":2,"dt_com":20250608190000,"enti_p":1,"enti_t":1,"perc":"13,29","vot_m":0,"vot_f":0,"vot_t":59,"perc_r":null},{"com":3,"dt_com":20250608230000,"enti_p":1,"enti_t":1,"perc":"18,69","vot_m":0,"vot_f":0,"vot_t":83,"perc_r":null},{"com":4,"dt_com":20250609150000,"enti_p":1,"enti_t":1,"perc":"27,03","vot_m":56,"vot_f":64,"vot_t":120,"perc_r":null}]}]}}
