{"int":{"st":"ESERCIZIO","c_ele":9,"t_ele":"Referendum","f_elet":"VOTANTI","dt_ele":20250608000000,"l_terr":"COMUNE","area":"I","dt_agg":20250609151404},"note":null,"scheda":[{"cod":2,"desc":null}],"enti":{"ente_p":{"desc":"BELVEDERE DI SPINELLO","cod":10,"ele_m":746,"ele_f":819,"ele_t":1565,"com":[{"cod_reg":18,"com_att":4,"num_com":4}],"com_vot":[{"com":1,"dt_com":20250608120000,"enti_p":3,"enti_t":3,"perc":"3,39","vot_m":0,"vot_f":0,"vot_t":53,"perc_r":null},{"com":2,"dt_com":20250608190000,"enti_p":3,"enti_t":3,"perc":"7,41","vot_m":0,"vot_f":0,"vot_t":116,"perc_r":null},{"com":3,"dt_com":20250608230000,"enti_p":3,"enti_t":3,"perc":"13,35","vot_m":0,"vot_f":0,"vot_t":209,"perc_r":null},{"com":4,"dt_com":20250609150000,"enti_p":3,"enti_t":3,"perc":"20,83","vot_m":164,"vot_f":162,"vot_t":326,"perc_r":null}]},"enti_f":[{"tipo":"SEZIONE","desc":"SEZIONE 1","cod":1,"osp":"N","ele_m":250,"ele_f":269,"ele_t":519,"com_vot":[{"com":1,"dt_com":20250608120000,"enti_p":1,"enti_t":1,"perc":"5,20","vot_m":0,"vot_f":0,"vot_t":27,"perc_r":null},{"com":2,"dt_com":20250608190000,"enti_p":1,"enti_t":1,"perc":"10,60","vot_m":0,"vot_f":0,"vot_t":55,"perc_r":null},{"com":3,"dt_com":20250608230000,"enti_p":1,"enti_t":1,"perc":"16,38","vot_m":0,"vot_f":0,"vot_t":85,"perc_r":null},{"com":4,"dt_com":20250609150000,"enti_p":1,"enti_t":1,"perc":"25,05","vot_m":66,"vot_f":64,"vot_t":130,"perc_r":null}]},{"tipo":"SEZIONE","desc":"SEZIONE 2","cod":2,"osp":"N","ele_m":244,"ele_f":284,"ele_t":528,"com_vot":[{"com":1,"dt_com":20250608120000,"enti_p":1,"enti_t":1,"perc":"2,46","vot_m":0,"vot_f":0,"vot_t":13,"perc_r":null},{"com":2,"dt_com":20250608190000,"enti_p":1,"enti_t":1,"perc":"4,92","vot_m":0,"vot_f":0,"vot_t":26,"perc_r":null},{"com":3,"dt_com":20250608230000,"enti_p":1,"enti_t":1,"perc":"9,47","vot_m":0,"vot_f":0,"vot_t":50,"perc_r":null},{"com":4,"dt_com":20250609150000,"enti_p":1,"enti_t":1,"perc":"13,26","vot_m":36,"vot_f":34,"vot_t":70,"perc_r":null}]},{"tipo":"SEZIONE","desc":"SEZIONE 3","cod":3,"osp":"N","ele_m":252,"ele_f":266,"ele_t":518,"com_vot":[{"com":1,"dt_com":20250608120000,"enti_p":1,"enti_t":1,"perc":"2,51","vot_m":0,"vot_f":0,"vot_t":13,"perc_r":null},{"com":2,"dt_com":20250608190000,"enti_p":1,"enti_t":1,"perc":"6,76","vot_m":0,"vot_f":0,"vot_t":35,"perc_r":null},{"com":3,"dt_com":20250608230000,"enti_p":1,"enti_t":1,"perc":"14,29","vot_m":0,"vot_f":0,"vot_t":74,"perc_r":null},{"com":4,"dt_com":20250609150000,"enti_p":1,"enti_t":1,"perc":"24,32","vot_m":62,"vot_f":64,"vot_t":126,"perc_r":null}]}]}}
